Workbook

Sheet Master
A1: Golf Betting Record - Outright
A2: Tour/Majors | B2: Tour/Majors
A3: Date (Year) | B3: DP World Tour | C3: LIV | D3: Majors | E3: Multiple | F3: Olympics | G3: PGA Tour | H3: Ryder Cup | I3: Grand Total
A4: 44927 | B4: 296.59 | C4: 120 | D4: -7.5 | E4: -21.35 | H4: 63.25 | I4: 450.99
A5: 45292 | B5: -72.47 | C5: -107.9 | D5: 156.06 | E5: -48.18 | F5: -24.37 | G5: 301.52 | I5: 204.66
A6: 45658 | B6: 27.5 | C6: -30 | D6: 111.35 | E6: -54 | G6: 307.15 | H6: 42.5 | I6: 404.5
A7: 46023 | E7: -20 | I7: -20
A8: Grand Total | B8: 251.62 | C8: -17.9 | D8: 259.91 | E8: -143.53 | F8: -24.37 | G8: 608.67 | H8: 105.75 | I8: 1040.15
J10: Overall - Combined Outright & multiples
J11: Category | K11: Total
J12: DP World Tour | K12: 251.62
J13: LIV | K13: -17.9
J14: Majors | K14: 259.91
J15: PGA Tour | K15: 608.67
J16: Ryder Cup | K16: 105.75
J17: Multiple | K17: -143.53
J18: Olympics | K18: -24.37
K19: {=SUM(K12:K18)} -> 1040.15
L21: Monthly ROI%
L22: Month | M22: Return On Investment
L23: 45078 | M23: 1.125
L24: 45108 | M24: -0.75181818
L25: 45170 | M25: 4.657602
L26: 45200 | M26: -1
L27: 45352 | M27: 4.4586667
L28: 45383 | M28: -0.0085432099
L29: 45413 | M29: -0.23770115
L30: 45444 | M30: 1.0022472
L31: 45474 | M31: 0.49833962
L32: 45505 | M32: 0.62256358
L33: 45536 | M33: -0.85327869
L34: 45566 | M34: -0.36660494
... L46: 45992 | M46: 0.53537736

Sheet Overall
A1: Date | B1: Tour/Majors | C1: Tournament | D1: Course | E1: Course Details | F1: Player | G1: Pre/Mid Tournament | H1: Type | I1: Price | J1: Place Terms | K1: Stake | L1: Bookmaker | M1: Result | N1: Outcome | O1: Return | P1: Profit/Loss | Q1: Tournament Winner | R1: Tournament Winner Odds | S1: Pre Tournament Notes | T1: Post Tournament Notes
A2: 09/07/2026 | B2: PGA Tour | C2: ISCO Championship | D2: Hurstbourne Country Club | E2: Course Hurstbourne Country Club, Louisville, Kentucky Length 7,056 yards Par 70 Course make-up two par-fives; 12 par-fours; four par-threes Course type Parkland Grass type Fairways: Meyer Zoysiagrass; Rough: Kentucky Bluegrass with Fine Fescue 4-6″; Greens: 4,750 sq.ft average featuring A1/A4 Bentgrass; Stimpmeter: 11ft. Course overview Keene Trace staged this event (previously called the Barbasol Championship) from 2018 to last year. The 2020 edition was cancelled due to Covid. Hurstbourne Country Club takes over for the first time this year. This short, tree-lined layout relies on water hazards and small greens to keep scoring in check. The fairways are zoysia grass and the greens are bentgrass. What will it take to win? This short, fiddly layout commands accurate approaches and smart scrambling around small greens | F2: Stephen Jaeger | G2: Pre | H2: First Round Leader E/W | I2: 45-1 | J2: N/A | K2: 5 | L2: Bet365 | M2: T1 | N2: Win | O2: 59.38 | P2: =SUM(O2-K2) -> 54.38 | Q2: Pending | R2: Pending | S2: Pending | T2: Pending
A3: 08/07/2026 | B3: DP World Tour | C3: Genesis Scottish Open | D3: The Renaissance Club | E3: Course The Renaissance Club, North Berwick, East Lothian, Scotland Length 7,282 yards Par 70 Course make-up Three par-fives; ten par-fours; five par-threes Course type Links Grass type Greens are fescue-based, similar to those used at Castle Stuart in this event in the relatively recent past, as well as at Royal Birkdale for the 2017 Open Championship. Course overview The Renaissance Club, which opened in 2008, was designed by Tom Doak. It made its Scottish Open debut in 2019, hosting every year since. Three holes run directly along the Firth of Forth, but this is not a pure links test, with some trees in strategic fairway and greenside positions. Heavily contoured greens are the main defence of the course What will it take to win? A strong short-game is a great asset on and around tricky greens. | F3: Davis Riley | G3: Pre | H3: First Round Leader E/W | I3: 325-1 | J3: 1/4 Top 5 | K3: 2.5 | L3: Coral | M3: N/A | N3: Loss | O3: 0 | P3: =SUM(O3-K3) -> -2.5 | Q3: Pending | R3: Pending | S3: Pending | T3: Pending
A4: 08/07/2026 | B4: DP World Tour | C4: Genesis Scottish Open | D4: The Renaissance Club | E4: Course The Renaissance Club, North Berwick, East Lothian, Scotland Length 7,282 yards Par 70 Course make-up Three par-fives; ten par-fours; five par-threes Course type Links Grass type Greens are fescue-based, similar to those used at Castle Stuart in this event in the relatively recent past, as well as at Royal Birkdale for the 2017 Open Championship. Course overview The Renaissance Club, which opened in 2008, was designed by Tom Doak. It made its Scottish Open debut in 2019, hosting every year since. Three holes run directly along the Firth of Forth, but this is not a pure links test, with some trees in strategic fairway and greenside positions. Heavily contoured greens are the main defence of the course What will it take to win? A strong short-game is a great asset on and around tricky greens. | F4: Calum Hill | G4: Pre | H4: First Round Leader E/W | I4: 140-1 | J4: 1/4 Top 5 | K4: 2.5 | L4: Coral | M4: N/A | N4: Loss | O4: 0 | P4: =SUM(O4-K4) -> -2.5 | Q4: Pending | R4: Pending | S4: Pending | T4: Pending
A5: 08/07/2026 | B5: DP World Tour | C5: Genesis Scottish Open | D5: The Renaissance Club | E5: Course The Renaissance Club, North Berwick, East Lothian, Scotland Length 7,282 yards Par 70 Course make-up Three par-fives; ten par-fours; five par-threes Course type Links Grass type Greens are fescue-based, similar to those used at Castle Stuart in this event in the relatively recent past, as well as at Royal Birkdale for the 2017 Open Championship. Course overview The Renaissance Club, which opened in 2008, was designed by Tom Doak. It made its Scottish Open debut in 2019, hosting every year since. Three holes run directly along the Firth of Forth, but this is not a pure links test, with some trees in strategic fairway and greenside positions. Heavily contoured greens are the main defence of the course What will it take to win? A strong short-game is a great asset on and around tricky greens. | F5: Wyndham Clark | G5: Pre | H5: First Round Leader E/W | I5: 45-1 | J5: 1/4 Top 5 | K5: 2.5 | L5: Coral | M5: N/A | N5: Loss | O5: 0 | P5: =SUM(O5-K5) -> -2.5 | Q5: Pending | R5: Pending | S5: Pending | T5: Pending
A6: 07/07/2026 | B6: PGA Tour | C6: ISCO Championship | D6: Hurstbourne Country Club | E6: Course Hurstbourne Country Club, Louisville, Kentucky Length 7,056 yards Par 70 Course make-up two par-fives; 12 par-fours; four par-threes Course type Parkland Grass type Fairways: Meyer Zoysiagrass; Rough: Kentucky Bluegrass with Fine Fescue 4-6″; Greens: 4,750 sq.ft average featuring A1/A4 Bentgrass; Stimpmeter: 11ft. Course overview Keene Trace staged this event (previously called the Barbasol Championship) from 2018 to last year. The 2020 edition was cancelled due to Covid. Hurstbourne Country Club takes over for the first time this year. This short, tree-lined layout relies on water hazards and small greens to keep scoring in check. The fairways are zoysia grass and the greens are bentgrass. What will it take to win? This short, fiddly layout commands accurate approaches and smart scrambling around small greens | F6: Max Homa | G6: Pre | H6: Outright | I6: 17-1 | J6: N/A | K6: 10 | L6: Bet365 | M6: Pending | N6: Pending | O6: 0 | P6: =SUM(O6-K6) -> -10 | Q6: Pending | R6: Pending | S6: Pending | T6: Pending
A7: 06/07/2026 | B7: DP World Tour | C7: Genesis Scottish Open | D7: The Renaissance Club | E7: Course The Renaissance Club, North Berwick, East Lothian, Scotland Length 7,282 yards Par 70 Course make-up Three par-fives; ten par-fours; five par-threes Course type Links Grass type Greens are fescue-based, similar to those used at Castle Stuart in this event in the relatively recent past, as well as at Royal Birkdale for the 2017 Open Championship. Course overview The Renaissance Club, which opened in 2008, was designed by Tom Doak. It made its Scottish Open debut in 2019, hosting every year since. Three holes run directly along the Firth of Forth, but this is not a pure links test, with some trees in strategic fairway and greenside positions. Heavily contoured greens are the main defence of the course What will it take to win? A strong short-game is a great asset on and around tricky greens. | F7: Wyndham Clark | G7: Pre | H7: E/W | I7: 28-1 | J7: 1/5 Top 8 | K7: 15 | L7: Bet365 | M7: Pending | N7: Pending | O7: 0 | P7: =SUM(O7-K7) -> -15 | Q7: Pending | R7: Pending | S7: Pending | T7: Pending
A8: 06/07/2026 | B8: DP World Tour | C8: Genesis Scottish Open | D8: The Renaissance Club | E8: Course The Renaissance Club, North Berwick, East Lothian, Scotland Length 7,282 yards Par 70 Course make-up Three par-fives; ten par-fours; five par-threes Course type Links Grass type Greens are fescue-based, similar to those used at Castle Stuart in this event in the relatively recent past, as well as at Royal Birkdale for the 2017 Open Championship. Course overview The Renaissance Club, which opened in 2008, was designed by Tom Doak. It made its Scottish Open debut in 2019, hosting every year since. Three holes run directly along the Firth of Forth, but this is not a pure links test, with some trees in strategic fairway and greenside positions. Heavily contoured greens are the main defence of the course What will it take to win? A strong short-game is a great asset on and around tricky greens. | F8: Bernd Wiesberger | G8: Pre | H8: E/W | I8: 150-1 | J8: 1/5 Top 10 | K8: 3.5 | L8: Bet365 | M8: Pending | N8: Pending | O8: 0 | P8: =SUM(O8-K8) -> -3.5 | Q8: Pending | R8: Pending | S8: Pending | T8: Pending
A9: 06/07/2026 | B9: DP World Tour | C9: Genesis Scottish Open | D9: The Renaissance Club | E9: Course The Renaissance Club, North Berwick, East Lothian, Scotland Length 7,282 yards Par 70 Course make-up Three par-fives; ten par-fours; five par-threes Course type Links Grass type Greens are fescue-based, similar to those used at Castle Stuart in this event in the relatively recent past, as well as at Royal Birkdale for the 2017 Open Championship. Course overview The Renaissance Club, which opened in 2008, was designed by Tom Doak. It made its Scottish Open debut in 2019, hosting every year since. Three holes run directly along the Firth of Forth, but this is not a pure links test, with some trees in strategic fairway and greenside positions. Heavily contoured greens are the main defence of the course What will it take to win? A strong short-game is a great asset on and around tricky greens. | F9: Victor Perez | G9: Pre | H9: E/W | I9: 130-1 | J9: 1/5 Top 10 | K9: 3.5 | L9: Coral | M9: Pending | N9: Pending | O9: 0 | P9: =SUM(O9-K9) -> -3.5 | Q9: Pending | R9: Pending | S9: Pending | T9: Pending
A10: 06/07/2026 | B10: DP World Tour | C10: Genesis Scottish Open | D10: The Renaissance Club | E10: Course The Renaissance Club, North Berwick, East Lothian, Scotland Length 7,282 yards Par 70 Course make-up Three par-fives; ten par-fours; five par-threes Course type Links Grass type Greens are fescue-based, similar to those used at Castle Stuart in this event in the relatively recent past, as well as at Royal Birkdale for the 2017 Open Championship. Course overview The Renaissance Club, which opened in 2008, was designed by Tom Doak. It made its Scottish Open debut in 2019, hosting every year since. Three holes run directly along the Firth of Forth, but this is not a pure links test, with some trees in strategic fairway and greenside positions. Heavily contoured greens are the main defence of the course What will it take to win? A strong short-game is a great asset on and around tricky greens. | F10: Matt Fitzpatrick | G10: Pre | H10: E/W | I10: 18-1 | J10: 1/5 Top 10 | K10: 20 | L10: Coral | M10: Pending | N10: Pending | O10: 0 | P10: =SUM(O10-K10) -> -20 | Q10: Pending | R10: Pending | S10: Pending | T10: Pending
A11: 06/07/2026 | B11: DP World Tour | C11: Genesis Scottish Open | D11: The Renaissance Club | E11: Course The Renaissance Club, North Berwick, East Lothian, Scotland Length 7,282 yards Par 70 Course make-up Three par-fives; ten par-fours; five par-threes Course type Links Grass type Greens are fescue-based, similar to those used at Castle Stuart in this event in the relatively recent past, as well as at Royal Birkdale for the 2017 Open Championship. Course overview The Renaissance Club, which opened in 2008, was designed by Tom Doak. It made its Scottish Open debut in 2019, hosting every year since. Three holes run directly along the Firth of Forth, but this is not a pure links test, with some trees in strategic fairway and greenside positions. Heavily contoured greens are the main defence of the course What will it take to win? A strong short-game is a great asset on and around tricky greens. | F11: Marco Penge | G11: Pre | H11: E/W | I11: 70-1 | J11: 1/5 Top 8 | K11: 7.5 | L11: Bet365 | M11: Pending | N11: Pending | O11: 0 | P11: =SUM(O11-K11) -> -7.5 | Q11: Pending | R11: Pending | S11: Pending | T11: Pending
A12: 01/07/2026 | B12: DP World Tour | C12: BMW International Open | D12: Golfclub Munchen Eichenried | E12: Course Golfclub Munchen Eichenried, Munich, Germany Length 7,347 yards Par 72 four par-fives; ten par-fours; four par-threes Course Make Up four par-fives; ten par-fours; four par-threes Course Type Parkland Grass Type Greens are Creeping Bentgrass Course Overview Eichenried has hosted this event 28 times, most recently from 1997 to 2011, then 2013, 2015, 2017 and from 2019 onwards. The flat, straightforward layout, with four par-fives reachable in two shots, has staged 11 rounds of 62. What will it take to win? History has proven that many types of players with different styles have succeeded here – it could be either a high GIR player who putts well, or someone in good putting. Form who finds more greens than normal who prevails. Either way, birdies and low scoring are the order of the day, particularly if rain does soften up the putting surfaces before the event as is forecast. | F12: Kazuma Kobori | G12: Pre | H12: First Round Leader E/W | I12: 70-1 | J12: 1/4 Top 5 | K12: 2.5 | L12: Coral | M12: N/A | N12: Loss | O12: 0 | P12: =SUM(O12-K12) -> -2.5 | Q12: Michael Hollick | R12: N/A | S12: Pending | T12: Pending
A13: 01/07/2026 | B13: DP World Tour | C13: BMW International Open | D13: Golfclub Munchen Eichenried | E13: Course Golfclub Munchen Eichenried, Munich, Germany Length 7,347 yards Par 72 four par-fives; ten par-fours; four par-threes Course Make Up four par-fives; ten par-fours; four par-threes Course Type Parkland Grass Type Greens are Creeping Bentgrass Course Overview Eichenried has hosted this event 28 times, most recently from 1997 to 2011, then 2013, 2015, 2017 and from 2019 onwards. The flat, straightforward layout, with four par-fives reachable in two shots, has staged 11 rounds of 62. What will it take to win? History has proven that many types of players with different styles have succeeded here – it could be either a high GIR player who putts well, or someone in good putting. Form who finds more greens than normal who prevails. Either way, birdies and low scoring are the order of the day, particularly if rain does soften up the putting surfaces before the event as is forecast. | F13: Calum Hill | G13: Pre | H13: First Round Leader E/W | I13: 66-1 | J13: 1/4 Top 5 | K13: 2.5 | L13: Coral | M13: N/A | N13: Loss | O13: 0 | P13: =SUM(O13-K13) -> -2.5 | Q13: Michael Hollick | R13: N/A | S13: Pending | T13: Pending
A14: 46204 | B14: PGA Tour | C14: John Deere Classic | D14: TPC Deere Run | E14: Course TPC Deere Run, Silvis, Illinois Length 7,327 yards Par 71 Course make-up Three par-fives; 11 par-fours; four par-threes Course type Parkland Grass type Fairways: Southshore Bentgrass; Rough: Kentucky Bluegrass with Fine Fescue 4″; Greens: 5,500 sq.ft average featuring L-93 Bentgrass; Stimpmeter: 11ft. Course overview The John Deere Classic has been held at TPC Deere Run since 2000. The track, crafted by DA Weibring in 1999, is one of the easiest the Tour stars face all season. The first and second holes are extremely simple, so there is scope for a fast start, and this is a birdiefest where only the hottest of putters will contend. What will it take to win? Steve Stricker, awesome with wedge in hand and one of the best putters in the world, won this event three times in a row before Zach Johnson, a player of a similar ilk, ended that streak. The John Deere lends itself to low scoring, with wedges and putter the key clubs in the bag | F14: Eric Cole | G14: Pre | H14: First Round Leader E/W | I14: 45-1 | J14: 1/5 Top 7 | K14: 2.5 | L14: Coral | M14: N/A | N14: Loss | O14: 0 | P14: =SUM(O14-K14) -> -2.5 | Q14: Chris Gotterup | R14: 16-1 | S14: Pending | T14: Pending
A15: 46204 | B15: PGA Tour | C15: John Deere Classic | D15: TPC Deere Run | E15: Course TPC Deere Run, Silvis, Illinois Length 7,327 yards Par 71 Course make-up Three par-fives; 11 par-fours; four par-threes Course type Parkland Grass type Fairways: Southshore Bentgrass; Rough: Kentucky Bluegrass with Fine Fescue 4″; Greens: 5,500 sq.ft average featuring L-93 Bentgrass; Stimpmeter: 11ft. Course overview The John Deere Classic has been held at TPC Deere Run since 2000. The track, crafted by DA Weibring in 1999, is one of the easiest the Tour stars face all season. The first and second holes are extremely simple, so there is scope for a fast start, and this is a birdiefest where only the hottest of putters will contend. What will it take to win? Steve Stricker, awesome with wedge in hand and one of the best putters in the world, won this event three times in a row before Zach Johnson, a player of a similar ilk, ended that streak. The John Deere lends itself to low scoring, with wedges and putter the key clubs in the bag | F15: Aldrich Potgieter | G15: Pre | H15: First Round Leader E/W | I15: 75-1 | J15: 1/5 Top 7 | K15: 2.5 | L15: Coral | M15: N/A | N15: Loss | O15: 0 | P15: =SUM(O15-K15) -> -2.5 | Q15: Chris Gotterup | R15: 16-1 | S15: Pending | T15: Pending
A16: 30/06/2026 | B16: DP World Tour | C16: BMW International Open | D16: Golfclub Munchen Eichenried | E16: Course Golfclub Munchen Eichenried, Munich, Germany Length 7,347 yards Par 72 four par-fives; ten par-fours; four par-threes Course Make Up four par-fives; ten par-fours; four par-threes Course Type Parkland Grass Type Greens are Creeping Bentgrass Course Overview Eichenried has hosted this event 28 times, most recently from 1997 to 2011, then 2013, 2015, 2017 and from 2019 onwards. The flat, straightforward layout, with four par-fives reachable in two shots, has staged 11 rounds of 62. What will it take to win? History has proven that many types of players with different styles have succeeded here – it could be either a high GIR player who putts well, or someone in good putting. Form who finds more greens than normal who prevails. Either way, birdies and low scoring are the order of the day, particularly if rain does soften up the putting surfaces before the event as is forecast. | F16: Oihan Guillamoundeguy | G16: Pre | H16: E/W | I16: 125-1 | J16: 1/5 Top 8 | K16: 2.5 | L16: Bet365 | M16: T4 | N16: Place | O16: 32.5 | P16: =SUM(O16-K16) -> 30 | Q16: Michael Hollick | R16: N/A | S16: Pending | T16: Pending
A17: 46203 | B17: DP World Tour | C17: BMW International Open | D17: Golfclub Munchen Eichenried | E17: Course Golfclub Munchen Eichenried, Munich, Germany Length 7,347 yards Par 72 four par-fives; ten par-fours; four par-threes Course Make Up four par-fives; ten par-fours; four par-threes Course Type Parkland Grass Type Greens are Creeping Bentgrass Course Overview Eichenried has hosted this event 28 times, most recently from 1997 to 2011, then 2013, 2015, 2017 and from 2019 onwards. The flat, straightforward layout, with four par-fives reachable in two shots, has staged 11 rounds of 62. What will it take to win? History has proven that many types of players with different styles have succeeded here – it could be either a high GIR player who putts well, or someone in good putting. Form who finds more greens than normal who prevails. Either way, birdies and low scoring are the order of the day, particularly if rain does soften up the putting surfaces before the event as is forecast. | F17: Marcus Armitage | G17: Pre | H17: E/W | I17: 66-1 | J17: 1/5 Top 8 | K17: 5 | L17: Bet365 | M17: T50 | N17: Loss | O17: 0 | P17: =SUM(O17-K17) -> -5 | Q17: Michael Hollick | R17: N/A | S17: Pending | T17: Pending
A18: 46203 | B18: Multiple | C18: John Deere Classic / BMW International Open | D18: N/A | E18: N/A | F18: Joaquin Niemann / Jackson Koivun | G18: Pre | H18: E/W Double | I18: 201-1 | J18: 1/4 Top 5 | K18: 5 | L18: Bet365 | M18: N/A | N18: Loss | O18: 0 | P18: =SUM(O18-K18) -> -5 | Q18: N/A | R18: N/A | S18: Pending | T18: Pending
A19: 46202 | B19: DP World Tour | C19: BMW International Open | D19: Golfclub Munchen Eichenried | E19: Course Golfclub Munchen Eichenried, Munich, Germany Length 7,347 yards Par 72 four par-fives; ten par-fours; four par-threes Course Make Up four par-fives; ten par-fours; four par-threes Course Type Parkland Grass Type Greens are Creeping Bentgrass Course Overview Eichenried has hosted this event 28 times, most recently from 1997 to 2011, then 2013, 2015, 2017 and from 2019 onwards. The flat, straightforward layout, with four par-fives reachable in two shots, has staged 11 rounds of 62. What will it take to win? History has proven that many types of players with different styles have succeeded here – it could be either a high GIR player who putts well, or someone in good putting. Form who finds more greens than normal who prevails. Either way, birdies and low scoring are the order of the day, particularly if rain does soften up the putting surfaces before the event as is forecast. | F19: Kazuma Kobori | G19: Pre | H19: E/W | I19: 55-1 | J19: 1/5 Top 8 | K19: 7.5 | L19: Betfred | M19: CUT | N19: Loss | O19: 0 | P19: =SUM(O19-K19) -> -7.5 | Q19: Michael Hollick | R19: N/A | S19: Pending | T19: Pending
A20: 46202 | B20: PGA Tour | C20: John Deere Classic | D20: TPC Deere Run | E20: Course TPC Deere Run, Silvis, Illinois Length 7,327 yards Par 71 Course make-up Three par-fives; 11 par-fours; four par-threes Course type Parkland Grass type Fairways: Southshore Bentgrass; Rough: Kentucky Bluegrass with Fine Fescue 4″; Greens: 5,500 sq.ft average featuring L-93 Bentgrass; Stimpmeter: 11ft. Course overview The John Deere Classic has been held at TPC Deere Run since 2000. The track, crafted by DA Weibring in 1999, is one of the easiest the Tour stars face all season. The first and second holes are extremely simple, so there is scope for a fast start, and this is a birdiefest where only the hottest of putters will contend. What will it take to win? Steve Stricker, awesome with wedge in hand and one of the best putters in the world, won this event three times in a row before Zach Johnson, a player of a similar ilk, ended that streak. The John Deere lends itself to low scoring, with wedges and putter the key clubs in the bag | F20: Aldrich Potgieter | G20: Pre | H20: E/W | I20: 45-1 | J20: 1/5 Top 8 | K20: 10 | L20: Coral | M20: CUT | N20: Loss | O20: 0 | P20: =SUM(O20-K20) -> -10 | Q20: Chris Gotterup | R20: 16-1 | S20: Pending | T20: Pending
A21: 46202 | B21: PGA Tour | C21: John Deere Classic | D21: TPC Deere Run | E21: Course TPC Deere Run, Silvis, Illinois Length 7,327 yards Par 71 Course make-up Three par-fives; 11 par-fours; four par-threes Course type Parkland Grass type Fairways: Southshore Bentgrass; Rough: Kentucky Bluegrass with Fine Fescue 4″; Greens: 5,500 sq.ft average featuring L-93 Bentgrass; Stimpmeter: 11ft. Course overview The John Deere Classic has been held at TPC Deere Run since 2000. The track, crafted by DA Weibring in 1999, is one of the easiest the Tour stars face all season. The first and second holes are extremely simple, so there is scope for a fast start, and this is a birdiefest where only the hottest of putters will contend. What will it take to win? Steve Stricker, awesome with wedge in hand and one of the best putters in the world, won this event three times in a row before Zach Johnson, a player of a similar ilk, ended that streak. The John Deere lends itself to low scoring, with wedges and putter the key clubs in the bag | F21: Jackson Koivun | G21: Pre | H21: E/W | I21: 20-1 | J21: 1/5 Top 10 | K21: 20 | L21: Coral | M21: CUT | N21: Loss | O21: 0 | P21: =SUM(O21-K21) -> -20 | Q21: Chris Gotterup | R21: 16-1 | S21: Pending | T21: Pending
A22: 46202 | B22: PGA Tour | C22: Travellers Championship | D22: TPC River Highlands | E22: Course TPC River Highlands, Cromwell, Connecticut Length 6,844 yards Par 70 Course make-up Two par-fives; 12 par-fours; four par-threes Course type Parkland Grass type Fairways: Bentgrass with Poa Annua; Rough: Kentucky Bluegrass with Fescue +4″; Greens: 5,000 sq.ft average featuring Bentgrass with Poa Annua; Tournament Stimp: 11ft. Course overview This Pete Dye creation has hosted this event since 1984, but it was redesigned in 1989, its name changing from TPC Connecticut to TPC River Highlands. Only the Phoenix Open attracts more spectators to a PGA Tour event than the Travelers What will it take to win? All types of player have succeeded at this venue – short-hitters like Olin Browne, Woody Austin, Ken Duke, Kevin Streelman, Russell Knox and Chez Reavie have won on the same terrain as bombers like Phil Mickelson, Bubba Watson and Dustin Johnson. Hitting plenty of greens and putting well is the route to success. Birdies aplenty are up for grabs, so weak putters will be left behind. | F22: Ryan Fox | G22: Pre | H22: First Round Leader E/W | I22: 70-1 | J22: 1/4 Top 5 | K22: 2.5 | L22: SkyBet | M22: N/A | N22: Loss | O22: 0 | P22: =SUM(O22-K22) -> -2.5 | Q22: Viktor Hovland | R22: 40-1 | S22: Pending | T22: Pending
A23: 46198 | B23: PGA Tour | C23: Travellers Championship | D23: TPC River Highlands | E23: Course TPC River Highlands, Cromwell, Connecticut Length 6,844 yards Par 70 Course make-up Two par-fives; 12 par-fours; four par-threes Course type Parkland Grass type Fairways: Bentgrass with Poa Annua; Rough: Kentucky Bluegrass with Fescue +4″; Greens: 5,000 sq.ft average featuring Bentgrass with Poa Annua; Tournament Stimp: 11ft. Course overview This Pete Dye creation has hosted this event since 1984, but it was redesigned in 1989, its name changing from TPC Connecticut to TPC River Highlands. Only the Phoenix Open attracts more spectators to a PGA Tour event than the Travelers What will it take to win? All types of player have succeeded at this venue – short-hitters like Olin Browne, Woody Austin, Ken Duke, Kevin Streelman, Russell Knox and Chez Reavie have won on the same terrain as bombers like Phil Mickelson, Bubba Watson and Dustin Johnson. Hitting plenty of greens and putting well is the route to success. Birdies aplenty are up for grabs, so weak putters will be left behind. | F23: Tom Hoge | G23: Pre | H23: First Round Leader E/W | I23: 125-1 | J23: 1/4 Top 5 | K23: 2.5 | L23: SkyBet | M23: N/A | N23: Loss | O23: 0 | P23: =SUM(O23-K23) -> -2.5 | Q23: Viktor Hovland | R23: 40-1 | S23: Pending | T23: Pending
A24: 46198 | B24: PGA Tour | C24: Travellers Championship | D24: TPC River Highlands | E24: Course TPC River Highlands, Cromwell, Connecticut Length 6,844 yards Par 70 Course make-up Two par-fives; 12 par-fours; four par-threes Course type Parkland Grass type Fairways: Bentgrass with Poa Annua; Rough: Kentucky Bluegrass with Fescue +4″; Greens: 5,000 sq.ft average featuring Bentgrass with Poa Annua; Tournament Stimp: 11ft. Course overview This Pete Dye creation has hosted this event since 1984, but it was redesigned in 1989, its name changing from TPC Connecticut to TPC River Highlands. Only the Phoenix Open attracts more spectators to a PGA Tour event than the Travelers What will it take to win? All types of player have succeeded at this venue – short-hitters like Olin Browne, Woody Austin, Ken Duke, Kevin Streelman, Russell Knox and Chez Reavie have won on the same terrain as bombers like Phil Mickelson, Bubba Watson and Dustin Johnson. Hitting plenty of greens and putting well is the route to success. Birdies aplenty are up for grabs, so weak putters will be left behind. | F24: Jackson Suber | G24: Pre | H24: First Round Leader E/W | I24: 90-1 | J24: 1/4 Top 5 | K24: 2.5 | L24: SkyBet | M24: N/A | N24: Loss | O24: 0 | P24: =SUM(O24-K24) -> -2.5 | Q24: Viktor Hovland | R24: 40-1 | S24: Pending | T24: Pending
A25: 46198 | B25: PGA Tour | C25: Travellers Championship | D25: TPC River Highlands | E25: Course TPC River Highlands, Cromwell, Connecticut Length 6,844 yards Par 70 Course make-up Two par-fives; 12 par-fours; four par-threes Course type Parkland Grass type Fairways: Bentgrass with Poa Annua; Rough: Kentucky Bluegrass with Fescue +4″; Greens: 5,000 sq.ft average featuring Bentgrass with Poa Annua; Tournament Stimp: 11ft. Course overview This Pete Dye creation has hosted this event since 1984, but it was redesigned in 1989, its name changing from TPC Connecticut to TPC River Highlands. Only the Phoenix Open attracts more spectators to a PGA Tour event than the Travelers What will it take to win? All types of player have succeeded at this venue – short-hitters like Olin Browne, Woody Austin, Ken Duke, Kevin Streelman, Russell Knox and Chez Reavie have won on the same terrain as bombers like Phil Mickelson, Bubba Watson and Dustin Johnson. Hitting plenty of greens and putting well is the route to success. Birdies aplenty are up for grabs, so weak putters will be left behind. | F25: Ben James | G25: Pre | H25: First Round Leader E/W | I25: 60-1 | J25: 1/4 Top 5 | K25: 0 | L25: SkyBet | M25: N/A | N25: Loss | O25: 0 | P25: =SUM(O25-K25) -> 0 | Q25: Viktor Hovland | R25: 40-1 | S25: Pending | T25: Pending
A26: 46198 | B26: PGA Tour | C26: Travellers Championship | D26: TPC River Highlands | E26: Course TPC River Highlands, Cromwell, Connecticut Length 6,844 yards Par 70 Course make-up Two par-fives; 12 par-fours; four par-threes Course type Parkland Grass type Fairways: Bentgrass with Poa Annua; Rough: Kentucky Bluegrass with Fescue +4″; Greens: 5,000 sq.ft average featuring Bentgrass with Poa Annua; Tournament Stimp: 11ft. Course overview This Pete Dye creation has hosted this event since 1984, but it was redesigned in 1989, its name changing from TPC Connecticut to TPC River Highlands. Only the Phoenix Open attracts more spectators to a PGA Tour event than the Travelers What will it take to win? All types of player have succeeded at this venue – short-hitters like Olin Browne, Woody Austin, Ken Duke, Kevin Streelman, Russell Knox and Chez Reavie have won on the same terrain as bombers like Phil Mickelson, Bubba Watson and Dustin Johnson. Hitting plenty of greens and putting well is the route to success. Birdies aplenty are up for grabs, so weak putters will be left behind. | F26: Eric Cole | G26: Pre | H26: First Round Leader E/W | I26: 50-1 | J26: 1/4 Top 5 | K26: 0 | L26: SkyBet | M26: 1 | N26: win | O26: 78.13 | P26: =SUM(O26-K26) -> 78.13 | Q26: Viktor Hovland | R26: 40-1 | S26: Pending | T26: Pending
A27: 46198 | B27: DP World Tour | C27: Italian Open | D27: Circolo Golf Torino | E27: Course The Blue Course at Circolo Golf Torino, Fiano, Italy Length 7,214 yards Par 71 Course make-up three par-fives; 12 par-fours; four par-threes Course type Parkland Grass type The course features Bentgrass greens and Bent/Poa grass fairways Course overview Set within the former royal hunting grounds of La Mandria near Turin, the fairways are framed by mature oak, chestnut and birch trees, creating tight driving corridors that place a greater emphasis on positioning than power. Designed by John Morrison and later refined by Michael Hurdzan and Dana Fry, this parkland course isn’t overly long by modern standards, placing a premium on strategy, accuracy and precise iron play. Three reachable par 5s offer the majority of the scoring opportunities, while a series of lengthy par 4s — most notably the 514-yard 12th — ensure players must combine strong driving with high-quality long-iron play. Bentgrass greens, narrow fairways and mature woodland create one of the most strategic tests on the DP World Tour schedule, favouring complete ball-strikers over outright power specialists. What will it take to win? Players who excel in finding fairways and consistently hitting greens in regulation are likely to enjoy a significant advantage over the week’s more aggressive bombers. | F27: Maximilian Steinlechner | G27: Pre | H27: First Round Leader E/W | I27: 100-1 | J27: 1/4 Top 5 | K27: 2.5 | L27: Coral | M27: N/A | N27: Loss | O27: 0 | P27: =SUM(O27-K27) -> -2.5 | Q27: Eugenio Chacarra | R27: 20-1 | S27: Pending | T27: Pending
A28: 46197 | B28: DP World Tour | C28: Italian Open | D28: Circolo Golf Torino | E28: Course The Blue Course at Circolo Golf Torino, Fiano, Italy Length 7,214 yards Par 71 Course make-up three par-fives; 12 par-fours; four par-threes Course type Parkland Grass type The course features Bentgrass greens and Bent/Poa grass fairways Course overview Set within the former royal hunting grounds of La Mandria near Turin, the fairways are framed by mature oak, chestnut and birch trees, creating tight driving corridors that place a greater emphasis on positioning than power. Designed by John Morrison and later refined by Michael Hurdzan and Dana Fry, this parkland course isn’t overly long by modern standards, placing a premium on strategy, accuracy and precise iron play. Three reachable par 5s offer the majority of the scoring opportunities, while a series of lengthy par 4s — most notably the 514-yard 12th — ensure players must combine strong driving with high-quality long-iron play. Bentgrass greens, narrow fairways and mature woodland create one of the most strategic tests on the DP World Tour schedule, favouring complete ball-strikers over outright power specialists. What will it take to win? Players who excel in finding fairways and consistently hitting greens in regulation are likely to enjoy a significant advantage over the week’s more aggressive bombers. | F28: Calum Hill | G28: Pre | H28: First Round Leader E/W | I28: 66-1 | J28: 1/4 Top 5 | K28: 2.5 | L28: Coral | M28: N/A | N28: Loss | O28: 0 | P28: =SUM(O28-K28) -> -2.5 | Q28: Eugenio Chacarra | R28: 20-1 | S28: Pending | T28: Pending
... A103: 46148 | B103: PGA Tour | C103: Truist Championship | D103: Quail Hollow Club | E103: Course Quail Hollow Club, Charlotte, North Carolina Length 7,583 yards Par 71 Course make up Three par-fives; 11 par-fours; four par-threes Course type Parkland Grass Type Fairways: 419 Bermudagrass overseeded with Perennial Ryegrass; Rough: 419 Bermudagrass overseeded with Perennial Ryegrass 2”; Greens: 6,578 sq.ft average featuring G12 Champion Bermudagrass overseeded with Poa Trivialis; Target Tournament Stimp: 12ft. Course overview Quail Hollow has hosted a regulation PGA Tour event every year since 2003 (Wachovia Championship, Quail Hollow Championship, Wells Fargo Championship), apart from 2017, 2020 (Covid), 2022 and last year. In 2017 and last year, the US PGA Championship was at Quail Hollow, then in 2022 the Presidents Cup was staged there. The course has been redesigned through the years. A renovation prior to the 2024 Wells Fargo switched the fairways to a new custom perennial ryegrass blend and the greens to TifEagle Bermuda, so form from the 2024 Wells Fargo and the 2025 US PGA is of most value to punters. What will it take to win the Truist? As with last week's Signature Event at Doral, another test of driving awaits. Long, straight hitting off the tee is the key to success at Quail Hollow. | F103: Xander Schauffele | G103: Pre | H103: Outright | I103: 12-1 | J103: N/A | K103: 10 | L103: SkyBet | M103: T60 | N103: Loss | O103: 0 | P103: =SUM(O103-K103) -> -10 | Q103: Kristopher Reitan | R103: 80-1 | S103: Pending | T103: Pending
A104: 46147 | B104: DP World Tour | C104: Estrella Damm Catalunya Championship | D104: Real Club de Golf El Prat | F104: Darius Van Driel | G104: Pre | H104: E/W | I104: 50-1 | J104: 1/5 Top 8 | K104: 7.5 | L104: Betfred | M104: CUT | N104: Loss | O104: 0 | P104: =SUM(O104-K104) -> -7.5 | Q104: Yurav Premlall | R104: N/A | S104: Pending | T104: Pending
A105: 46146 | B105: PGA Tour | C105: Myrtle Beach Classic | D105: The Dunes Golf and Beach Club | E105: Course The Dunes Golf and Beach Club, Myrtle Beach, South Carolina Length 7,347 yards Par 71 – three par-fives; 11 par-fours; four par-threes Time difference South Carolina is five hours behind the UK and Ireland Course type Parkland Grass Type Fairways: Ryegrass overseed; Rough: Bermudagrass overseeded with Perennial Ryegrass 2.5″; Greens: 6,000 sq.ft average featuring Champion UltraDwarf Bermudagrass. Course overview The largely tree-lined Robert Jones Senior designed Dunes Club made its PGA Tour debut last year. It runs alongside Lake Singleton and water comes into play on most holes. The average winning total in the six editions of the Champions Tour event staged there (Senior Tour Championship, 1994 through 1999) was 12 under par, but Chris Gotterup romped to 22 under par 12 months ago Type of player suited to the challenge Generous fairways and wide greens should result in low scoring, so expect an attacking powerhouse to prevail, as was the case last year Key attribute Power | F105: Steven Fisk | G105: Pre | H105: E/W | I105: 35-1 | J105: 1/5 Top 8 | K105: 10 | L105: Bet365 | M105: T38 | N105: Loss | O105: 0 | P105: =SUM(O105-K105) -> -10 | Q105: Brandt Snedeker | R105: 175-1 | S105: Pending | T105: Pending
A106: 46146 | B106: PGA Tour | C106: Truist Championship | D106: Quail Hollow Club | E106: Course Quail Hollow Club, Charlotte, North Carolina Length 7,583 yards Par 71 Course make up Three par-fives; 11 par-fours; four par-threes Course type Parkland Grass Type Fairways: 419 Bermudagrass overseeded with Perennial Ryegrass; Rough: 419 Bermudagrass overseeded with Perennial Ryegrass 2”; Greens: 6,578 sq.ft average featuring G12 Champion Bermudagrass overseeded with Poa Trivialis; Target Tournament Stimp: 12ft. Course overview Quail Hollow has hosted a regulation PGA Tour event every year since 2003 (Wachovia Championship, Quail Hollow Championship, Wells Fargo Championship), apart from 2017, 2020 (Covid), 2022 and last year. In 2017 and last year, the US PGA Championship was at Quail Hollow, then in 2022 the Presidents Cup was staged there. The course has been redesigned through the years. A renovation prior to the 2024 Wells Fargo switched the fairways to a new custom perennial ryegrass blend and the greens to TifEagle Bermuda, so form from the 2024 Wells Fargo and the 2025 US PGA is of most value to punters. What will it take to win the Truist? As with last week's Signature Event at Doral, another test of driving awaits. Long, straight hitting off the tee is the key to success at Quail Hollow. | F106: Aldrich Potgieter | G106: Pre | H106: E/W | I106: 140-1 | J106: 1/5 Top 8 | K106: 2.5 | L106: Coral | M106: T48 | N106: Loss | O106: 0 | P106: =SUM(O106-K106) -> -2.5 | Q106: Kristopher Reitan | R106: 80-1 | S106: Pending | T106: Pending
A107: 46146 | B107: PGA Tour | C107: Truist Championship | D107: Quail Hollow Club | E107: Course Quail Hollow Club, Charlotte, North Carolina Length 7,583 yards Par 71 Course make up Three par-fives; 11 par-fours; four par-threes Course type Parkland Grass Type Fairways: 419 Bermudagrass overseeded with Perennial Ryegrass; Rough: 419 Bermudagrass overseeded with Perennial Ryegrass 2”; Greens: 6,578 sq.ft average featuring G12 Champion Bermudagrass overseeded with Poa Trivialis; Target Tournament Stimp: 12ft. Course overview Quail Hollow has hosted a regulation PGA Tour event every year since 2003 (Wachovia Championship, Quail Hollow Championship, Wells Fargo Championship), apart from 2017, 2020 (Covid), 2022 and last year. In 2017 and last year, the US PGA Championship was at Quail Hollow, then in 2022 the Presidents Cup was staged there. The course has been redesigned through the years. A renovation prior to the 2024 Wells Fargo switched the fairways to a new custom perennial ryegrass blend and the greens to TifEagle Bermuda, so form from the 2024 Wells Fargo and the 2025 US PGA is of most value to punters. What will it take to win the Truist? As with last week's Signature Event at Doral, another test of driving awaits. Long, straight hitting off the tee is the key to success at Quail Hollow. | F107: Sahith Theegala | G107: Pre | H107: E/W | I107: 80-1 | J107: 1/5 Top 8 | K107: 5 | L107: Coral | M107: 69 | N107: Loss | O107: 0 | P107: =SUM(O107-K107) -> -5 | Q107: Kristopher Reitan | R107: 80-1 | S107: Pending | T107: Pending
A108: 46146 | B108: PGA Tour | C108: Truist Championship | D108: Quail Hollow Club | E108: Course Quail Hollow Club, Charlotte, North Carolina Length 7,583 yards Par 71 Course make up Three par-fives; 11 par-fours; four par-threes Course type Parkland Grass Type Fairways: 419 Bermudagrass overseeded with Perennial Ryegrass; Rough: 419 Bermudagrass overseeded with Perennial Ryegrass 2”; Greens: 6,578 sq.ft average featuring G12 Champion Bermudagrass overseeded with Poa Trivialis; Target Tournament Stimp: 12ft. Course overview Quail Hollow has hosted a regulation PGA Tour event every year since 2003 (Wachovia Championship, Quail Hollow Championship, Wells Fargo Championship), apart from 2017, 2020 (Covid), 2022 and last year. In 2017 and last year, the US PGA Championship was at Quail Hollow, then in 2022 the Presidents Cup was staged there. The course has been redesigned through the years. A renovation prior to the 2024 Wells Fargo switched the fairways to a new custom perennial ryegrass blend and the greens to TifEagle Bermuda, so form from the 2024 Wells Fargo and the 2025 US PGA is of most value to punters. What will it take to win the Truist? As with last week's Signature Event at Doral, another test of driving awaits. Long, straight hitting off the tee is the key to success at Quail Hollow. | F108: Ben Griffin | G108: Pre | H108: E/W | I108: 35-1 | J108: 1/5 Top 8 | K108: 10 | L108: Coral | M108: T63 | N108: Loss | O108: 0 | P108: =SUM(O108-K108) -> -10 | Q108: Kristopher Reitan | R108: 80-1 | S108: Pending | T108: Pending
A109: 46146 | B109: DP World Tour | C109: Turkish Airlines Open | D109: Trump National Doral | E109: Course Blue Monster Course, Trump National Doral, Miami, Florida Length 7,739 yards Par 72 Course make up Four par-fives; ten par-fours; four par-threes Course type Parkland Grass type Fairways: Bermudagrass; Rough: Bermudagrass 3″; Greens: TifEagle Bermudagrass; Tournament Stimp: 11-11.5 ft. Course Overview The Blue Monster hosted the Doral Open/Ford Championship/CA Championship on the PGA Tour from 1962 to 2006. From 2007 through 2016, it hosted the WGC-Cadillac Championship. Gil Hanse redesigned the Blue Monster before the 2014 Cadillac. Dick Wilson's famous track had been getting too easy, the ancient layout providing something far from monstrous for professionals with modern equipment in their hands, underlined by a 2013 winning score of 19 under par from Tiger Woods. Donald Trump funded a $200m upgrade to bolster Doral and Hanse announced afterwards: “It's pretty much a brand-new golf course.” Every hole was changed and the toughened-up track produced a four-under-par winning total in 2014. Adam Scott won the last WGC-Cadillac with a 12-under-par total. The last two events at this course were the 2024 and 2025 LIV Miami – 54-hole events won by Dean Burmester and Marc Leishman. What will it take to win? Course form prior to 2014 is of limited value. Length off the tee is extremely beneficial on the revised layout. Expect powerhouses to dominate in fine weather. | F109: Bernd Wiesberger | G109: Pre | H109: First Round Leader E/W | I109: 50-1 | J109: 1/4 Top 5 | K109: 2.5 | L109: Bet365 | M109: N/A | N109: Loss | O109: 0 | P109: =SUM(O109-K109) -> -2.5 | Q109: Mikael Lindberg | R109: 40-1 | S109: Pending | T109: Pending
A110: 46141 | B110: DP World Tour | C110: Turkish Airlines Open | D110: Trump National Doral | E110: Course Blue Monster Course, Trump National Doral, Miami, Florida Length 7,739 yards Par 72 Course make up Four par-fives; ten par-fours; four par-threes Course type Parkland Grass type Fairways: Bermudagrass; Rough: Bermudagrass 3″; Greens: TifEagle Bermudagrass; Tournament Stimp: 11-11.5 ft. Course Overview The Blue Monster hosted the Doral Open/Ford Championship/CA Championship on the PGA Tour from 1962 to 2006. From 2007 through 2016, it hosted the WGC-Cadillac Championship. Gil Hanse redesigned the Blue Monster before the 2014 Cadillac. Dick Wilson's famous track had been getting too easy, the ancient layout providing something far from monstrous for professionals with modern equipment in their hands, underlined by a 2013 winning score of 19 under par from Tiger Woods. Donald Trump funded a $200m upgrade to bolster Doral and Hanse announced afterwards: “It's pretty much a brand-new golf course.” Every hole was changed and the toughened-up track produced a four-under-par winning total in 2014. Adam Scott won the last WGC-Cadillac with a 12-under-par total. The last two events at this course were the 2024 and 2025 LIV Miami – 54-hole events won by Dean Burmester and Marc Leishman. What will it take to win? Course form prior to 2014 is of limited value. Length off the tee is extremely beneficial on the revised layout. Expect powerhouses to dominate in fine weather. | F110: Kiradech Aphibarnrat | G110: Pre | H110: First Round Leader E/W | I110: 80-1 | J110: 1/4 Top 5 | K110: 2.5 | L110: Bet365 | M110: N/A | N110: Loss | O110: 0 | P110: =SUM(O110-K110) -> -2.5 | Q110: Mikael Lindberg | R110: 40-1 | S110: Pending | T110: Pending
A111: 46141 | B111: PGA Tour | C111: Cadillac Championship | D111: Trump National Doral | E111: Course Blue Monster Course, Trump National Doral, Miami, Florida Length 7,739 yards Par 72 Course make up Four par-fives; ten par-fours; four par-threes Course type Parkland Grass type Fairways: Bermudagrass; Rough: Bermudagrass 3″; Greens: TifEagle Bermudagrass; Tournament Stimp: 11-11.5 ft. Course Overview The Blue Monster hosted the Doral Open/Ford Championship/CA Championship on the PGA Tour from 1962 to 2006. From 2007 through 2016, it hosted the WGC-Cadillac Championship. Gil Hanse redesigned the Blue Monster before the 2014 Cadillac. Dick Wilson's famous track had been getting too easy, the ancient layout providing something far from monstrous for professionals with modern equipment in their hands, underlined by a 2013 winning score of 19 under par from Tiger Woods. Donald Trump funded a $200m upgrade to bolster Doral and Hanse announced afterwards: “It's pretty much a brand-new golf course.” Every hole was changed and the toughened-up track produced a four-under-par winning total in 2014. Adam Scott won the last WGC-Cadillac with a 12-under-par total. The last two events at this course were the 2024 and 2025 LIV Miami – 54-hole events won by Dean Burmester and Marc Leishman. What will it take to win? Course form prior to 2014 is of limited value. Length off the tee is extremely beneficial on the revised layout. Expect powerhouses to dominate in fine weather. | F111: Pierceson Coody | G111: Pre | H111: First Round Leader E/W | I111: 50-1 | J111: 1/4 Top 5 | K111: 2.5 | L111: Bet365 | M111: N/A | N111: Loss | O111: 0 | P111: =SUM(O111-K111) -> -2.5 | Q111: Cameron Young | R111: 12-1 | S111: Pending | T111: Pending
A112: 46141 | B112: PGA Tour | C112: Cadillac Championship | D112: Trump National Doral | E112: Course Blue Monster Course, Trump National Doral, Miami, Florida Length 7,739 yards Par 72 Course make up Four par-fives; ten par-fours; four par-threes Course type Parkland Grass type Fairways: Bermudagrass; Rough: Bermudagrass 3″; Greens: TifEagle Bermudagrass; Tournament Stimp: 11-11.5 ft. Course Overview The Blue Monster hosted the Doral Open/Ford Championship/CA Championship on the PGA Tour from 1962 to 2006. From 2007 through 2016, it hosted the WGC-Cadillac Championship. Gil Hanse redesigned the Blue Monster before the 2014 Cadillac. Dick Wilson's famous track had been getting too easy, the ancient layout providing something far from monstrous for professionals with modern equipment in their hands, underlined by a 2013 winning score of 19 under par from Tiger Woods. Donald Trump funded a $200m upgrade to bolster Doral and Hanse announced afterwards: “It's pretty much a brand-new golf course.” Every hole was changed and the toughened-up track produced a four-under-par winning total in 2014. Adam Scott won the last WGC-Cadillac with a 12-under-par total. The last two events at this course were the 2024 and 2025 LIV Miami – 54-hole events won by Dean Burmester and Marc Leishman. What will it take to win? Course form prior to 2014 is of limited value. Length off the tee is extremely beneficial on the revised layout. Expect powerhouses to dominate in fine weather. | F112: Jhonattan Vegas | G112: Pre | H112: First Round Leader E/W | I112: 110-1 | J112: 1/4 Top 5 | K112: 2.5 | L112: Bet365 | M112: N/A | N112: Loss | O112: 0 | P112: =SUM(O112-K112) -> -2.5 | Q112: Cameron Young | R112: 12-1 | S112: Pending | T112: Pending
A113: 46141 | B113: Multiple | C113: Cadillac Championship / Turkish Airlines Open | D113: N/A | E113: N/A | F113: Scottie Scheffler / David Puig | G113: Pre | H113: Outright | I113: 43-1 | J113: N/A | K113: 5 | L113: SkyBet | M113: N/A | N113: Loss | O113: 0 | P113: =SUM(O113-K113) -> -5 | Q113: N/A | R113: N/A | S113: Pending | T113: Pending
A114: 46140 | B114: PGA Tour | C114: Cadillac Championship | D114: Trump National Doral | E114: Course Blue Monster Course, Trump National Doral, Miami, Florida Length 7,739 yards Par 72 Course make up Four par-fives; ten par-fours; four par-threes Course type Parkland Grass type Fairways: Bermudagrass; Rough: Bermudagrass 3″; Greens: TifEagle Bermudagrass; Tournament Stimp: 11-11.5 ft. Course Overview The Blue Monster hosted the Doral Open/Ford Championship/CA Championship on the PGA Tour from 1962 to 2006. From 2007 through 2016, it hosted the WGC-Cadillac Championship. Gil Hanse redesigned the Blue Monster before the 2014 Cadillac. Dick Wilson's famous track had been getting too easy, the ancient layout providing something far from monstrous for professionals with modern equipment in their hands, underlined by a 2013 winning score of 19 under par from Tiger Woods. Donald Trump funded a $200m upgrade to bolster Doral and Hanse announced afterwards: “It's pretty much a brand-new golf course.” Every hole was changed and the toughened-up track produced a four-under-par winning total in 2014. Adam Scott won the last WGC-Cadillac with a 12-under-par total. The last two events at this course were the 2024 and 2025 LIV Miami – 54-hole events won by Dean Burmester and Marc Leishman. What will it take to win? Course form prior to 2014 is of limited value. Length off the tee is extremely beneficial on the revised layout. Expect powerhouses to dominate in fine weather. | F114: Chris Gotterup | G114: Pre | H114: E/W | I114: 22-1 | J114: 1/5 Top 8 | K114: 15 | L114: Coral | M114: T38 | N114: Loss | O114: 0 | P114: =SUM(O114-K114) -> -15 | Q114: Cameron Young | R114: 12-1 | S114: Pending | T114: Pending
A115: 46139 | B115: DP World Tour | C115: Turkish Airlines Open | F115: Ricardo Gouveia | G115: Pre | H115: E/W | I115: 200-1 | J115: 1/5 Top 10 | K115: 2.5 | L115: Bet365 | M115: T7 | N115: Place | O115: 51.25 | P115: =SUM(O115-K115) -> 48.75 | Q115: Mikael Lindberg | R115: 40-1 | S115: Pending | T115: Pending
A116: 46139 | B116: DP World Tour | C116: Turkish Airlines Open | F116: Davis Bryant | G116: Pre | H116: E/W | I116: 80-1 | J116: 1/5 Top 8 | K116: 5 | L116: Betfred | M116: T29 | N116: Loss | O116: 0 | P116: =SUM(O116-K116) -> -5 | Q116: Mikael Lindberg | R116: 40-1 | S116: Pending | T116: Pending
A117: 46139 | B117: PGA Tour | C117: Cadillac Championship | D117: Trump National Doral | E117: Course Blue Monster Course, Trump National Doral, Miami, Florida Length 7,739 yards Par 72 Course make up Four par-fives; ten par-fours; four par-threes Course type Parkland Grass type Fairways: Bermudagrass; Rough: Bermudagrass 3″; Greens: TifEagle Bermudagrass; Tournament Stimp: 11-11.5 ft. Course Overview The Blue Monster hosted the Doral Open/Ford Championship/CA Championship on the PGA Tour from 1962 to 2006. From 2007 through 2016, it hosted the WGC-Cadillac Championship. Gil Hanse redesigned the Blue Monster before the 2014 Cadillac. Dick Wilson's famous track had been getting too easy, the ancient layout providing something far from monstrous for professionals with modern equipment in their hands, underlined by a 2013 winning score of 19 under par from Tiger Woods. Donald Trump funded a $200m upgrade to bolster Doral and Hanse announced afterwards: “It's pretty much a brand-new golf course.” Every hole was changed and the toughened-up track produced a four-under-par winning total in 2014. Adam Scott won the last WGC-Cadillac with a 12-under-par total. The last two events at this course were the 2024 and 2025 LIV Miami – 54-hole events won by Dean Burmester and Marc Leishman. What will it take to win? Course form prior to 2014 is of limited value. Length off the tee is extremely beneficial on the revised layout. Expect powerhouses to dominate in fine weather. | F117: Harris English | G117: Pre | H117: E/W | I117: 35-1 | J117: 1/5 Top 8 | K117: 10 | L117: Coral | M117: T55 | N117: Loss | O117: 0 | P117: =SUM(O117-K117) -> -10 | Q117: Cameron Young | R117: 12-1 | S117: Pending | T117: Pending
A118: 46139 | B118: DP World Tour | C118: Turkish Airlines Open | F118: Francesco Molinari | G118: Pre | H118: E/W | I118: 55-1 | J118: 1/5 Top 8 | K118: 7.5 | L118: SkyBet | M118: CUT | N118: Loss | O118: 0 | P118: =SUM(O118-K118) -> -7.5 | Q118: Mikael Lindberg | R118: 40-1 | S118: Pending | T118: Pending
A119: 46139 | B119: DP World Tour | C119: Turkish Airlines Open | F119: Nathan Kimsey | G119: Pre | H119: E/W | I119: 40-1 | J119: 1/5 Top 8 | K119: 10 | L119: Betfred | M119: T29 | N119: Loss | O119: 0 | P119: =SUM(O119-K119) -> -10 | Q119: Mikael Lindberg | R119: 40-1 | S119: Pending | T119: Pending
A120: 46139 | B120: DP World Tour | C120: Volvo China Open | D120: Enhance Anting Golf Club | E120: Course Enhance Anting Golf Club, Shanghai, China Length 7,168 yards Par 71 – three par-five holes, 11 par-fours, four par-threes Time difference China is seven hours ahead of the UK and Ireland Course type Parkland Course overview The Robert Trent Jones Junior-designed Enhance Anting is a flat track hosting for the first time this week. A feature of the layout are enormous water hazards, creating lots of risk-reward options. The tree-lined fairways demand accurate driving Type of player suited to the challenge Accurate driving and approach-play seems the key to success at this new DP World Tour venue Key attribute Accuracy | F120: Alejandro Del Rey | G120: Pre | H120: First Round Leader E/W | I120: 55-1 | J120: 1/4 Top 5 | K120: 5 | L120: Betfred | M120: 1 | N120: Win | O120: 178.87 | P120: =SUM(O120-K120) -> 173.87 | Q120: Bernd Wiesberger | R120: 80-1 | S120: Pending | T120: Pending
A121: 46134 | B121: DP World Tour | C121: Volvo China Open | D121: Enhance Anting Golf Club | E121: Course Enhance Anting Golf Club, Shanghai, China Length 7,168 yards Par 71 – three par-five holes, 11 par-fours, four par-threes Time difference China is seven hours ahead of the UK and Ireland Course type Parkland Course overview The Robert Trent Jones Junior-designed Enhance Anting is a flat track hosting for the first time this week. A feature of the layout are enormous water hazards, creating lots of risk-reward options. The tree-lined fairways demand accurate driving Type of player suited to the challenge Accurate driving and approach-play seems the key to success at this new DP World Tour venue Key attribute Accuracy | F121: Eugenio Chacarra | G121: Pre | H121: First Round Leader E/W | I121: 33-1 | J121: 1/4 Top 5 | K121: 5 | L121: Betfred | M121: N/A | N121: Loss | O121: 0 | P121: =SUM(O121-K121) -> -5 | Q121: Bernd Wiesberger | R121: 80-1 | S121: Pending | T121: Pending
A122: 46134 | B122: DP World Tour | C122: Volvo China Open | D122: Enhance Anting Golf Club | E122: Course Enhance Anting Golf Club, Shanghai, China Length 7,168 yards Par 71 – three par-five holes, 11 par-fours, four par-threes Time difference China is seven hours ahead of the UK and Ireland Course type Parkland Course overview The Robert Trent Jones Junior-designed Enhance Anting is a flat track hosting for the first time this week. A feature of the layout are enormous water hazards, creating lots of risk-reward options. The tree-lined fairways demand accurate driving Type of player suited to the challenge Accurate driving and approach-play seems the key to success at this new DP World Tour venue Key attribute Accuracy | F122: Romain Langasque | G122: Pre | H122: E/W | I122: 55-1 | J122: 1/5 Top 8 | K122: 5 | L122: Betfred | M122: T52 | N122: Loss | O122: 0 | P122: =SUM(O122-K122) -> -5 | Q122: Bernd Wiesberger | R122: 80-1 | S122: Pending | T122: Pending
A123: 46134 | B123: DP World Tour | C123: Volvo China Open | D123: Enhance Anting Golf Club | E123: Course Enhance Anting Golf Club, Shanghai, China Length 7,168 yards Par 71 – three par-five holes, 11 par-fours, four par-threes Time difference China is seven hours ahead of the UK and Ireland Course type Parkland Course overview The Robert Trent Jones Junior-designed Enhance Anting is a flat track hosting for the first time this week. A feature of the layout are enormous water hazards, creating lots of risk-reward options. The tree-lined fairways demand accurate driving Type of player suited to the challenge Accurate driving and approach-play seems the key to success at this new DP World Tour venue Key attribute Accuracy | F123: Federic LaCroix | G123: Pre | H123: E/W | I123: 45-1 | J123: 1/5 Top 8 | K123: 5 | L123: Bet365 | M123: CUT | N123: Loss | O123: 0 | P123: =SUM(O123-K123) -> -5 | Q123: Bernd Wiesberger | R123: 80-1 | S123: Pending | T123: Pending
A124: 46134 | B124: DP World Tour | C124: Volvo China Open | D124: Enhance Anting Golf Club | E124: Course Enhance Anting Golf Club, Shanghai, China Length 7,168 yards Par 71 – three par-five holes, 11 par-fours, four par-threes Time difference China is seven hours ahead of the UK and Ireland Course type Parkland Course overview The Robert Trent Jones Junior-designed Enhance Anting is a flat track hosting for the first time this week. A feature of the layout are enormous water hazards, creating lots of risk-reward options. The tree-lined fairways demand accurate driving Type of player suited to the challenge Accurate driving and approach-play seems the key to success at this new DP World Tour venue Key attribute Accuracy | F124: Wenyi Ding | G124: Pre | H124: E/W | I124: 20-1 | J124: 1/5 Top 8 | K124: 10 | L124: Bet365 | M124: T25 | N124: Loss | O124: 0 | P124: =SUM(O124-K124) -> -10 | Q124: Bernd Wiesberger | R124: 80-1 | S124: Pending | T124: Pending
A125: 46134 | B125: PGA Tour | C125: RBC Heritage | D125: Harbour Town Golf Links | E125: Course Harbour Town Links, Hilton Head Island, South Carolina Length 7,243 yards Par 71 Course make up Three par-five holes; 11 par-fours; four par-threes Course type Links Grass type Fairways: Celebration Bermudagrass overseeded with Perennial Ryegrass; Rough: Celebration Bermudagrass overseeded with Perennial Ryegrass 1.5″; Greens: 3,700 sq.ft average TifEagle Bermudagrass overseeded with Poa Trivialis; Tournament Stimp: 11-11.5 ft. Course overview Harbour Town Links is a Pete Dye design, created in 1969, revised in 2000 and restored with subtle changes by Davis Love since last year's event. Players will only score well with straight hitting to tight targets and good scrambling around some of the smallest greens on the circuit. The Heritage was given Signature Event status for the first time in 2023, with a reduced field size What will it take to win The Heritage? Accurate approaches to tiny greens are essential for success. Sharp scramblers also prosper | F125: Viktor Hovland | G125: Pre | H125: First Round Leader E/W | I125: 40-1 | J125: 1/4 Top 5 | K125: 2.5 | L125: Bet365 | M125: T2 | N125: Place | O125: 12.19 | P125: =SUM(O125-K125) -> 9.69 | Q125: Matt Fitzpatrick | R125: 16-1 | S125: - Weather looks good, should be dry, warm with some breeze on Thursday and weekend afternoons. - Tight OTT, some of the smallest greens on tour. Accuracy and GIR%/APP required to win here. - Only 2 of the last 10 winners finished in top10 at Augusta, and two not even playing the masters prior. - Correlation between the Copperhead Course (Valspar Championship) & Colonial (Charles Schwab). - [x] Austin Smotherman, good APP and driving acc, one previous start here in 2023, T67. Career has moved up a gear since and could go well at a long price in limited field. - [ ] Jacob Bridgeman - [x] Matt Fitzpatrick comes into this in fantastic form, winning the valspar and previous to that a close 2nd in the players. 4th APP, 3rd T2G, 7th Driving accuracy. On top of a great record here, winning in 2024 and 4th in 2021. An average masters tournament last week but I’m not too concerned about that, not sure he has quite the game to wear the green jacket. The obvious choice for me this week away from short priced Scottie. Great chance. - [x] Ryo Hisatsune has moved up a level this year with some great results and regularly topping leaderboards, just struggling to get the job done but he’s not far away. T18 on debut here last year, could go well again at a decent price. - [x] Maverick McNealy having a good start of the year. 5 out of 10 starts so far this year he’s finished in the top20. Decent effort at the Masters finishing T18. Has good form round here finishing 3rd in 2025, if he can get off to a good start he should be right in the mix come Sunday. | T125: A lovely little winner for us as Matt Fitzpatrick saw off Scottie in a playoff down the 18th with a lovely birdie. Fitz built up a 3 shot lead after Saturday round, two early birdies in the 4th round followed by a long string of pars up till the 18th which he duffed his chip and resulting in a playoff finish. Until Sunday Fitzy was superior with 65 &63 on first two rounds really set him up for the win taking advantage of the calm conditions on the first two days. The other three were quite disappointing. Mav McNealy started with a 74, followed by three 67s, playing good golf but another sluggish start puts him out of contention. Smotherman and Hisatsune bottom of the leaderboard. Eye Catchers - Harris English coming into form after a mediocre start to the season.
A126: 46128 | B126: PGA Tour | C126: RBC Heritage | D126: Harbour Town Golf Links | E126: Course Harbour Town Links, Hilton Head Island, South Carolina Length 7,243 yards Par 71 Course make up Three par-five holes; 11 par-fours; four par-threes Course type Links Grass type Fairways: Celebration Bermudagrass overseeded with Perennial Ryegrass; Rough: Celebration Bermudagrass overseeded with Perennial Ryegrass 1.5″; Greens: 3,700 sq.ft average TifEagle Bermudagrass overseeded with Poa Trivialis; Tournament Stimp: 11-11.5 ft. Course overview Harbour Town Links is a Pete Dye design, created in 1969, revised in 2000 and restored with subtle changes by Davis Love since last year's event. Players will only score well with straight hitting to tight targets and good scrambling around some of the smallest greens on the circuit. The Heritage was given Signature Event status for the first time in 2023, with a reduced field size What will it take to win The Heritage? Accurate approaches to tiny greens are essential for success. Sharp scramblers also prosper | F126: Sepp Straka | G126: Pre | H126: First Round Leader E/W | I126: 40-1 | J126: 1/4 Top 5 | K126: 2.5 | L126: Betfred | M126: N/A | N126: Loss | O126: 0 | P126: =SUM(O126-K126) -> -2.5 | Q126: Matt Fitzpatrick | R126: 16-1 | S126: - Weather looks good, should be dry, warm with some breeze on Thursday and weekend afternoons. - Tight OTT, some of the smallest greens on tour. Accuracy and GIR%/APP required to win here. - Only 2 of the last 10 winners finished in top10 at Augusta, and two not even playing the masters prior. - Correlation between the Copperhead Course (Valspar Championship) & Colonial (Charles Schwab). - [x] Austin Smotherman, good APP and driving acc, one previous start here in 2023, T67. Career has moved up a gear since and could go well at a long price in limited field. - [ ] Jacob Bridgeman - [x] Matt Fitzpatrick comes into this in fantastic form, winning the valspar and previous to that a close 2nd in the players. 4th APP, 3rd T2G, 7th Driving accuracy. On top of a great record here, winning in 2024 and 4th in 2021. An average masters tournament last week but I’m not too concerned about that, not sure he has quite the game to wear the green jacket. The obvious choice for me this week away from short priced Scottie. Great chance. - [x] Ryo Hisatsune has moved up a level this year with some great results and regularly topping leaderboards, just struggling to get the job done but he’s not far away. T18 on debut here last year, could go well again at a decent price. - [x] Maverick McNealy having a good start of the year. 5 out of 10 starts so far this year he’s finished in the top20. Decent effort at the Masters finishing T18. Has good form round here finishing 3rd in 2025, if he can get off to a good start he should be right in the mix come Sunday. | T126: A lovely little winner for us as Matt Fitzpatrick saw off Scottie in a playoff down the 18th with a lovely birdie. Fitz built up a 3 shot lead after Saturday round, two early birdies in the 4th round followed by a long string of pars up till the 18th which he duffed his chip and resulting in a playoff finish. Until Sunday Fitzy was superior with 65 &63 on first two rounds really set him up for the win taking advantage of the calm conditions on the first two days. The other three were quite disappointing. Mav McNealy started with a 74, followed by three 67s, playing good golf but another sluggish start puts him out of contention. Smotherman and Hisatsune bottom of the leaderboard. Eye Catchers - Harris English coming into form after a mediocre start to the season.
A127: 46128 | B127: PGA Tour | C127: RBC Heritage | D127: Harbour Town Golf Links | E127: Course Harbour Town Links, Hilton Head Island, South Carolina Length 7,243 yards Par 71 Course make up Three par-five holes; 11 par-fours; four par-threes Course type Links Grass type Fairways: Celebration Bermudagrass overseeded with Perennial Ryegrass; Rough: Celebration Bermudagrass overseeded with Perennial Ryegrass 1.5″; Greens: 3,700 sq.ft average TifEagle Bermudagrass overseeded with Poa Trivialis; Tournament Stimp: 11-11.5 ft. Course overview Harbour Town Links is a Pete Dye design, created in 1969, revised in 2000 and restored with subtle changes by Davis Love since last year's event. Players will only score well with straight hitting to tight targets and good scrambling around some of the smallest greens on the circuit. The Heritage was given Signature Event status for the first time in 2023, with a reduced field size What will it take to win The Heritage? Accurate approaches to tiny greens are essential for success. Sharp scramblers also prosper | F127: Austin Smotherman | G127: Pre | H127: First Round Leader E/W | I127: 100-1 | J127: 1/4 Top 5 | K127: 2.5 | L127: Bet365 | M127: N/A | N127: Loss | O127: 0 | P127: =SUM(O127-K127) -> -2.5 | Q127: Matt Fitzpatrick | R127: 16-1 | S127: - Weather looks good, should be dry, warm with some breeze on Thursday and weekend afternoons. - Tight OTT, some of the smallest greens on tour. Accuracy and GIR%/APP required to win here. - Only 2 of the last 10 winners finished in top10 at Augusta, and two not even playing the masters prior. - Correlation between the Copperhead Course (Valspar Championship) & Colonial (Charles Schwab). - [x] Austin Smotherman, good APP and driving acc, one previous start here in 2023, T67. Career has moved up a gear since and could go well at a long price in limited field. - [ ] Jacob Bridgeman - [x] Matt Fitzpatrick comes into this in fantastic form, winning the valspar and previous to that a close 2nd in the players. 4th APP, 3rd T2G, 7th Driving accuracy. On top of a great record here, winning in 2024 and 4th in 2021. An average masters tournament last week but I’m not too concerned about that, not sure he has quite the game to wear the green jacket. The obvious choice for me this week away from short priced Scottie. Great chance. - [x] Ryo Hisatsune has moved up a level this year with some great results and regularly topping leaderboards, just struggling to get the job done but he’s not far away. T18 on debut here last year, could go well again at a decent price. - [x] Maverick McNealy having a good start of the year. 5 out of 10 starts so far this year he’s finished in the top20. Decent effort at the Masters finishing T18. Has good form round here finishing 3rd in 2025, if he can get off to a good start he should be right in the mix come Sunday. | T127: A lovely little winner for us as Matt Fitzpatrick saw off Scottie in a playoff down the 18th with a lovely birdie. Fitz built up a 3 shot lead after Saturday round, two early birdies in the 4th round followed by a long string of pars up till the 18th which he duffed his chip and resulting in a playoff finish. Until Sunday Fitzy was superior with 65 &63 on first two rounds really set him up for the win taking advantage of the calm conditions on the first two days. The other three were quite disappointing. Mav McNealy started with a 74, followed by three 67s, playing good golf but another sluggish start puts him out of contention. Smotherman and Hisatsune bottom of the leaderboard. Eye Catchers - Harris English coming into form after a mediocre start to the season.
A128: 46128 | B128: PGA Tour | C128: RBC Heritage | D128: Harbour Town Golf Links | E128: Course Harbour Town Links, Hilton Head Island, South Carolina Length 7,243 yards Par 71 Course make up Three par-five holes; 11 par-fours; four par-threes Course type Links Grass type Fairways: Celebration Bermudagrass overseeded with Perennial Ryegrass; Rough: Celebration Bermudagrass overseeded with Perennial Ryegrass 1.5″; Greens: 3,700 sq.ft average TifEagle Bermudagrass overseeded with Poa Trivialis; Tournament Stimp: 11-11.5 ft. Course overview Harbour Town Links is a Pete Dye design, created in 1969, revised in 2000 and restored with subtle changes by Davis Love since last year's event. Players will only score well with straight hitting to tight targets and good scrambling around some of the smallest greens on the circuit. The Heritage was given Signature Event status for the first time in 2023, with a reduced field size What will it take to win The Heritage? Accurate approaches to tiny greens are essential for success. Sharp scramblers also prosper | F128: Maverick McNealy | G128: Pre | H128: First Round Leader E/W | I128: 35-1 | J128: 1/4 Top 5 | K128: 2.5 | L128: Betfred | M128: N/A | N128: Loss | O128: 0 | P128: =SUM(O128-K128) -> -2.5 | Q128: Matt Fitzpatrick | R128: 16-1 | S128: - Weather looks good, should be dry, warm with some breeze on Thursday and weekend afternoons. - Tight OTT, some of the smallest greens on tour. Accuracy and GIR%/APP required to win here. - Only 2 of the last 10 winners finished in top10 at Augusta, and two not even playing the masters prior. - Correlation between the Copperhead Course (Valspar Championship) & Colonial (Charles Schwab). - [x] Austin Smotherman, good APP and driving acc, one previous start here in 2023, T67. Career has moved up a gear since and could go well at a long price in limited field. - [ ] Jacob Bridgeman - [x] Matt Fitzpatrick comes into this in fantastic form, winning the valspar and previous to that a close 2nd in the players. 4th APP, 3rd T2G, 7th Driving accuracy. On top of a great record here, winning in 2024 and 4th in 2021. An average masters tournament last week but I’m not too concerned about that, not sure he has quite the game to wear the green jacket. The obvious choice for me this week away from short priced Scottie. Great chance. - [x] Ryo Hisatsune has moved up a level this year with some great results and regularly topping leaderboards, just struggling to get the job done but he’s not far away. T18 on debut here last year, could go well again at a decent price. - [x] Maverick McNealy having a good start of the year. 5 out of 10 starts so far this year he’s finished in the top20. Decent effort at the Masters finishing T18. Has good form round here finishing 3rd in 2025, if he can get off to a good start he should be right in the mix come Sunday. | T128: A lovely little winner for us as Matt Fitzpatrick saw off Scottie in a playoff down the 18th with a lovely birdie. Fitz built up a 3 shot lead after Saturday round, two early birdies in the 4th round followed by a long string of pars up till the 18th which he duffed his chip and resulting in a playoff finish. Until Sunday Fitzy was superior with 65 &63 on first two rounds really set him up for the win taking advantage of the calm conditions on the first two days. The other three were quite disappointing. Mav McNealy started with a 74, followed by three 67s, playing good golf but another sluggish start puts him out of contention. Smotherman and Hisatsune bottom of the leaderboard. Eye Catchers - Harris English coming into form after a mediocre start to the season.
A129: 46128 | B129: PGA Tour | C129: RBC Heritage | D129: Harbour Town Golf Links | E129: Course Harbour Town Links, Hilton Head Island, South Carolina Length 7,243 yards Par 71 Course make up Three par-five holes; 11 par-fours; four par-threes Course type Links Grass type Fairways: Celebration Bermudagrass overseeded with Perennial Ryegrass; Rough: Celebration Bermudagrass overseeded with Perennial Ryegrass 1.5″; Greens: 3,700 sq.ft average TifEagle Bermudagrass overseeded with Poa Trivialis; Tournament Stimp: 11-11.5 ft. Course overview Harbour Town Links is a Pete Dye design, created in 1969, revised in 2000 and restored with subtle changes by Davis Love since last year's event. Players will only score well with straight hitting to tight targets and good scrambling around some of the smallest greens on the circuit. The Heritage was given Signature Event status for the first time in 2023, with a reduced field size What will it take to win The Heritage? Accurate approaches to tiny greens are essential for success. Sharp scramblers also prosper | F129: Maverick McNealy | G129: Pre | H129: E/W | I129: 30-1 | J129: 1/5 Top 8 | K129: 15 | L129: Bet365 | M129: T16 | N129: Loss | O129: 0 | P129: =SUM(O129-K129) -> -15 | Q129: Matt Fitzpatrick | R129: 16-1 | S129: - Weather looks good, should be dry, warm with some breeze on Thursday and weekend afternoons. - Tight OTT, some of the smallest greens on tour. Accuracy and GIR%/APP required to win here. - Only 2 of the last 10 winners finished in top10 at Augusta, and two not even playing the masters prior. - Correlation between the Copperhead Course (Valspar Championship) & Colonial (Charles Schwab). - [x] Austin Smotherman, good APP and driving acc, one previous start here in 2023, T67. Career has moved up a gear since and could go well at a long price in limited field. - [ ] Jacob Bridgeman - [x] Matt Fitzpatrick comes into this in fantastic form, winning the valspar and previous to that a close 2nd in the players. 4th APP, 3rd T2G, 7th Driving accuracy. On top of a great record here, winning in 2024 and 4th in 2021. An average masters tournament last week but I’m not too concerned about that, not sure he has quite the game to wear the green jacket. The obvious choice for me this week away from short priced Scottie. Great chance. - [x] Ryo Hisatsune has moved up a level this year with some great results and regularly topping leaderboards, just struggling to get the job done but he’s not far away. T18 on debut here last year, could go well again at a decent price. - [x] Maverick McNealy having a good start of the year. 5 out of 10 starts so far this year he’s finished in the top20. Decent effort at the Masters finishing T18. Has good form round here finishing 3rd in 2025, if he can get off to a good start he should be right in the mix come Sunday. | T129: A lovely little winner for us as Matt Fitzpatrick saw off Scottie in a playoff down the 18th with a lovely birdie. Fitz built up a 3 shot lead after Saturday round, two early birdies in the 4th round followed by a long string of pars up till the 18th which he duffed his chip and resulting in a playoff finish. Until Sunday Fitzy was superior with 65 &63 on first two rounds really set him up for the win taking advantage of the calm conditions on the first two days. The other three were quite disappointing. Mav McNealy started with a 74, followed by three 67s, playing good golf but another sluggish start puts him out of contention. Smotherman and Hisatsune bottom of the leaderboard. Eye Catchers - Harris English coming into form after a mediocre start to the season.
A130: 46125 | B130: PGA Tour | C130: RBC Heritage | D130: Harbour Town Golf Links | E130: Course Harbour Town Links, Hilton Head Island, South Carolina Length 7,243 yards Par 71 Course make up Three par-five holes; 11 par-fours; four par-threes Course type Links Grass type Fairways: Celebration Bermudagrass overseeded with Perennial Ryegrass; Rough: Celebration Bermudagrass overseeded with Perennial Ryegrass 1.5″; Greens: 3,700 sq.ft average TifEagle Bermudagrass overseeded with Poa Trivialis; Tournament Stimp: 11-11.5 ft. Course overview Harbour Town Links is a Pete Dye design, created in 1969, revised in 2000 and restored with subtle changes by Davis Love since last year's event. Players will only score well with straight hitting to tight targets and good scrambling around some of the smallest greens on the circuit. The Heritage was given Signature Event status for the first time in 2023, with a reduced field size What will it take to win The Heritage? Accurate approaches to tiny greens are essential for success. Sharp scramblers also prosper | F130: Austin Smotherman | G130: Pre | H130: E/W | I130: 125-1 | J130: 1/5 Top 10 | K130: 5 | L130: Bet365 | M130: T74 | N130: Loss | O130: 0 | P130: =SUM(O130-K130) -> -5 | Q130: Matt Fitzpatrick | R130: 16-1 | S130: - Weather looks good, should be dry, warm with some breeze on Thursday and weekend afternoons. - Tight OTT, some of the smallest greens on tour. Accuracy and GIR%/APP required to win here. - Only 2 of the last 10 winners finished in top10 at Augusta, and two not even playing the masters prior. - Correlation between the Copperhead Course (Valspar Championship) & Colonial (Charles Schwab). - [x] Austin Smotherman, good APP and driving acc, one previous start here in 2023, T67. Career has moved up a gear since and could go well at a long price in limited field. - [ ] Jacob Bridgeman - [x] Matt Fitzpatrick comes into this in fantastic form, winning the valspar and previous to that a close 2nd in the players. 4th APP, 3rd T2G, 7th Driving accuracy. On top of a great record here, winning in 2024 and 4th in 2021. An average masters tournament last week but I’m not too concerned about that, not sure he has quite the game to wear the green jacket. The obvious choice for me this week away from short priced Scottie. Great chance. - [x] Ryo Hisatsune has moved up a level this year with some great results and regularly topping leaderboards, just struggling to get the job done but he’s not far away. T18 on debut here last year, could go well again at a decent price. - [x] Maverick McNealy having a good start of the year. 5 out of 10 starts so far this year he’s finished in the top20. Decent effort at the Masters finishing T18. Has good form round here finishing 3rd in 2025, if he can get off to a good start he should be right in the mix come Sunday. | T130: A lovely little winner for us as Matt Fitzpatrick saw off Scottie in a playoff down the 18th with a lovely birdie. Fitz built up a 3 shot lead after Saturday round, two early birdies in the 4th round followed by a long string of pars up till the 18th which he duffed his chip and resulting in a playoff finish. Until Sunday Fitzy was superior with 65 &63 on first two rounds really set him up for the win taking advantage of the calm conditions on the first two days. The other three were quite disappointing. Mav McNealy started with a 74, followed by three 67s, playing good golf but another sluggish start puts him out of contention. Smotherman and Hisatsune bottom of the leaderboard. Eye Catchers - Harris English coming into form after a mediocre start to the season.
A131: 46125 | B131: PGA Tour | C131: RBC Heritage | D131: Harbour Town Golf Links | E131: Course Harbour Town Links, Hilton Head Island, South Carolina Length 7,243 yards Par 71 Course make up Three par-five holes; 11 par-fours; four par-threes Course type Links Grass type Fairways: Celebration Bermudagrass overseeded with Perennial Ryegrass; Rough: Celebration Bermudagrass overseeded with Perennial Ryegrass 1.5″; Greens: 3,700 sq.ft average TifEagle Bermudagrass overseeded with Poa Trivialis; Tournament Stimp: 11-11.5 ft. Course overview Harbour Town Links is a Pete Dye design, created in 1969, revised in 2000 and restored with subtle changes by Davis Love since last year's event. Players will only score well with straight hitting to tight targets and good scrambling around some of the smallest greens on the circuit. The Heritage was given Signature Event status for the first time in 2023, with a reduced field size What will it take to win The Heritage? Accurate approaches to tiny greens are essential for success. Sharp scramblers also prosper | F131: Ryo Hisatsune | G131: Pre | H131: E/W | I131: 55-1 | J131: 1/5 Top 8 | K131: 10 | L131: Coral | M131: T60 | N131: Loss | O131: 0 | P131: =SUM(O131-K131) -> -10 | Q131: Matt Fitzpatrick | R131: 16-1 | S131: - Weather looks good, should be dry, warm with some breeze on Thursday and weekend afternoons. - Tight OTT, some of the smallest greens on tour. Accuracy and GIR%/APP required to win here. - Only 2 of the last 10 winners finished in top10 at Augusta, and two not even playing the masters prior. - Correlation between the Copperhead Course (Valspar Championship) & Colonial (Charles Schwab). - [x] Austin Smotherman, good APP and driving acc, one previous start here in 2023, T67. Career has moved up a gear since and could go well at a long price in limited field. - [ ] Jacob Bridgeman - [x] Matt Fitzpatrick comes into this in fantastic form, winning the valspar and previous to that a close 2nd in the players. 4th APP, 3rd T2G, 7th Driving accuracy. On top of a great record here, winning in 2024 and 4th in 2021. An average masters tournament last week but I’m not too concerned about that, not sure he has quite the game to wear the green jacket. The obvious choice for me this week away from short priced Scottie. Great chance. - [x] Ryo Hisatsune has moved up a level this year with some great results and regularly topping leaderboards, just struggling to get the job done but he’s not far away. T18 on debut here last year, could go well again at a decent price. - [x] Maverick McNealy having a good start of the year. 5 out of 10 starts so far this year he’s finished in the top20. Decent effort at the Masters finishing T18. Has good form round here finishing 3rd in 2025, if he can get off to a good start he should be right in the mix come Sunday. | T131: A lovely little winner for us as Matt Fitzpatrick saw off Scottie in a playoff down the 18th with a lovely birdie. Fitz built up a 3 shot lead after Saturday round, two early birdies in the 4th round followed by a long string of pars up till the 18th which he duffed his chip and resulting in a playoff finish. Until Sunday Fitzy was superior with 65 &63 on first two rounds really set him up for the win taking advantage of the calm conditions on the first two days. The other three were quite disappointing. Mav McNealy started with a 74, followed by three 67s, playing good golf but another sluggish start puts him out of contention. Smotherman and Hisatsune bottom of the leaderboard. Eye Catchers - Harris English coming into form after a mediocre start to the season.
... A158: 46104 | B158: DP World Tour | C158: Hero Indian Open | D158: DLF Golf & Country Club | E158: Course Signature Course, DLF Golf and Country Club, New Delhi, India Length 7,416 yards Par 72 Course make-up Four par-five holes; ten par-fours; four par-threes Course type Parkland Grass type Bermudagrass has been used throughout the construction with Mini Verde the strain of choice on the greens. Course overview DLF G&CC's Signature Course hosted this event in 2017, 2018, 2019, 2023, 2024 and last year, as well as an Asian Tour event (International Series India) in February last year. Gary Player created the layout in 2015. The layout is 700 feet above sea level, providing more carry, but serious troublespots lurk on every hole and the greens are full of grain. What will it take to win Indian Open? The modern DLF is long and difficult, demanding accuracy from tee to green and great touch on the sloping, grainy greens. | F158: Adrian Otaegui | G158: Pre | H158: E/W | I158: 50-1 | J158: 1/5 Top 8 | K158: 7.5 | L158: SkyBet | M158: T61 | N158: Loss | O158: 0 | P158: =SUM(O158-K158) -> -7.5 | Q158: Alex Fitzpatrick | R158: 25-1 | S158: Pending | T158: Pending
A159: 46104 | B159: N/A | C159: Valspar Championship / Hainan Classic | D159: N/A | F159: Xander Schauffele / Grant Forrest | G159: Pre | H159: E/W Double | I159: 79-1 | J159: 1/4 Top 5 | K159: 2.5 | L159: Bet365 | M159: N/A | N159: Loss | O159: 0 | P159: =SUM(O159-K159) -> -2.5 | Q159: N/A | R159: N/A | S159: N/A | T159: N/A
A160: 46100 | B160: PGA Tour | C160: Valspar Championship | D160: Innisbrook Resort (Copperhead Course) | E160: Course Copperhead, Innisbrook Resort, Palm Harbor, Florida Length 7,352 yards Par 71 Course make up Four par-fives; nine par-fours; five par-threes Course type Parkland Grass type Fairways: Celebration Bermudagrass overseeded with Ryegrass; Rough: Celebration Bermudagrass overseeded with Ryegrass 3.75″; Greens: 5,822 sq.ft average featuring TifEagle Bermudagrass with Poa Trivialis overseed; Tournament Stimp: 12ft. Course overview This is a tough, tree-lined layout, with thick rough, hosting for the 25th time (there was no tournament in 2001 or 2020). The event was formerly known as the Tampa Bay Classic, Chrysler Championship, PODS Championship, Transitions Championship and Tampa Bay Championship. What will it take to win the Valspar? Straight hitting and churning out greens in regulation on a tight course with lots of doglegs is the key to success, which is why players such as KJ Choi, Retief Goosen, Jim Furyk, Kevin Streelman, John Senden and Adam Hadwin have flourished in the past. | F160: Kevin Roy | G160: Pre | H160: First Round Leader E/W | I160: 100-1 | J160: 1/5 Top 7 | K160: 2.5 | L160: Bet365 | M160: N/A | N160: Loss | O160: 0 | P160: =SUM(O160-K160) -> -2.5 | Q160: Matt Fitzpatrick | R160: 12-1 | S160: - Accuracy is key round here, looking for strong APP GIR% - Dry, sunny conditions. Windy on Thursday, calm rest of the week. - [x] Xander, had a tournament low round of 66 in R4. Finished T3 at the players, where he was 1st APP and T5 GIR%. Looks back to his best and a dangerous threat around a course that should suit. - [ ] Ricky Castillo - [ ] Bridgeman - [ ] Hisatsune - [x] William Mouw - [x] Justin Thomas | T160: Pending
A161: 46100 | B161: PGA Tour | C161: Valspar Championship | D161: Innisbrook Resort (Copperhead Course) | E161: Course Copperhead, Innisbrook Resort, Palm Harbor, Florida Length 7,352 yards Par 71 Course make up Four par-fives; nine par-fours; five par-threes Course type Parkland Grass type Fairways: Celebration Bermudagrass overseeded with Ryegrass; Rough: Celebration Bermudagrass overseeded with Ryegrass 3.75″; Greens: 5,822 sq.ft average featuring TifEagle Bermudagrass with Poa Trivialis overseed; Tournament Stimp: 12ft. Course overview This is a tough, tree-lined layout, with thick rough, hosting for the 25th time (there was no tournament in 2001 or 2020). The event was formerly known as the Tampa Bay Classic, Chrysler Championship, PODS Championship, Transitions Championship and Tampa Bay Championship. What will it take to win the Valspar? Straight hitting and churning out greens in regulation on a tight course with lots of doglegs is the key to success, which is why players such as KJ Choi, Retief Goosen, Jim Furyk, Kevin Streelman, John Senden and Adam Hadwin have flourished in the past. | F161: Justin Thomas | G161: Pre | H161: First Round Leader E/W | I161: 35-1 | J161: 1/5 Top 7 | K161: 5 | L161: Bet365 | M161: N/A | N161: Loss | O161: 0 | P161: =SUM(O161-K161) -> -5 | Q161: Matt Fitzpatrick | R161: 12-1 | S161: - Accuracy is key round here, looking for strong APP GIR% - Dry, sunny conditions. Windy on Thursday, calm rest of the week. - [x] Xander, had a tournament low round of 66 in R4. Finished T3 at the players, where he was 1st APP and T5 GIR%. Looks back to his best and a dangerous threat around a course that should suit. - [ ] Ricky Castillo - [ ] Bridgeman - [ ] Hisatsune - [x] William Mouw - [x] Justin Thomas | T161: Pending
A162: 46100 | B162: PGA Tour | C162: Valspar Championship | D162: Innisbrook Resort (Copperhead Course) | E162: Course Copperhead, Innisbrook Resort, Palm Harbor, Florida Length 7,352 yards Par 71 Course make up Four par-fives; nine par-fours; five par-threes Course type Parkland Grass type Fairways: Celebration Bermudagrass overseeded with Ryegrass; Rough: Celebration Bermudagrass overseeded with Ryegrass 3.75″; Greens: 5,822 sq.ft average featuring TifEagle Bermudagrass with Poa Trivialis overseed; Tournament Stimp: 12ft. Course overview This is a tough, tree-lined layout, with thick rough, hosting for the 25th time (there was no tournament in 2001 or 2020). The event was formerly known as the Tampa Bay Classic, Chrysler Championship, PODS Championship, Transitions Championship and Tampa Bay Championship. What will it take to win the Valspar? Straight hitting and churning out greens in regulation on a tight course with lots of doglegs is the key to success, which is why players such as KJ Choi, Retief Goosen, Jim Furyk, Kevin Streelman, John Senden and Adam Hadwin have flourished in the past. | F162: Justin Thomas | G162: Pre | H162: E/W | I162: 22-1 | J162: 1/5 Top 8 | K162: 15 | L162: Bet365 | M162: T30 | N162: Loss | O162: 0 | P162: =SUM(O162-K162) -> -15 | Q162: Matt Fitzpatrick | R162: 12-1 | S162: - Accuracy is key round here, looking for strong APP GIR% - Dry, sunny conditions. Windy on Thursday, calm rest of the week. - [x] Xander, had a tournament low round of 66 in R4. Finished T3 at the players, where he was 1st APP and T5 GIR%. Looks back to his best and a dangerous threat around a course that should suit. - [ ] Ricky Castillo - [ ] Bridgeman - [ ] Hisatsune - [x] William Mouw - [x] Justin Thomas | T162: Pending
A163: 46097 | B163: DP World Tour | C163: Hainan Classic | D163: Blackstone Course, Mission Hills Resort Haikou | E163: Course Blackstone and Vintage Courses, Mission Hills, Hainan, China Length Blackstone - 7,637 yards, Vintage - 7,331 yards Par Both 72 – four par-fives, ten par-fours, four par-threes Course type Both parkland Course overview This is the second time Mission Hills has hosted the Hainan Classic and while all four rounds were played on the Blackstone Course last year, the Vintage Course will be used as well this time, so each of the 120 players will play both courses in the opening two days. This change has enabled amateur players to be involved and reduced the professional field to 120. The Blackstone has wide fairways and is the significantly longer of the two, while the Vintage represents a different challenge with plenty of doglegs and blind shots to be negotiated on the tree-lined track that is heavily bunkered. Type of player suited to the challenge Penge drove and putted well to come out on top last year and length off the tee is usually a key skill on Chinese courses. The Vintage is a bit more fiddly, but will only have to be navigated once. Key attribute Power | F163: Grant Forrest | G163: Pre | H163: E/W | I163: 25-1 | J163: 1/5 Top 8 | K163: 10 | L163: SkyBet | M163: T66 | N163: Loss | O163: 0 | P163: =SUM(O163-K163) -> -10 | Q163: Jordan Gumberg | R163: 90-1 | S163: Pending | T163: Pending
A164: 46097 | B164: DP World Tour | C164: Hainan Classic | D164: Blackstone Course, Mission Hills Resort Haikou | E164: Course Blackstone and Vintage Courses, Mission Hills, Hainan, China Length Blackstone - 7,637 yards, Vintage - 7,331 yards Par Both 72 – four par-fives, ten par-fours, four par-threes Course type Both parkland Course overview This is the second time Mission Hills has hosted the Hainan Classic and while all four rounds were played on the Blackstone Course last year, the Vintage Course will be used as well this time, so each of the 120 players will play both courses in the opening two days. This change has enabled amateur players to be involved and reduced the professional field to 120. The Blackstone has wide fairways and is the significantly longer of the two, while the Vintage represents a different challenge with plenty of doglegs and blind shots to be negotiated on the tree-lined track that is heavily bunkered. Type of player suited to the challenge Penge drove and putted well to come out on top last year and length off the tee is usually a key skill on Chinese courses. The Vintage is a bit more fiddly, but will only have to be navigated once. Key attribute Power | F164: Mikael Lindberg | G164: Pre | H164: E/W | I164: 28-1 | J164: 1/5 Top 8 | K164: 10 | L164: SkyBet | M164: T45 | N164: Loss | O164: 0 | P164: =SUM(O164-K164) -> -10 | Q164: Jordan Gumberg | R164: 90-1 | S164: Pending | T164: Pending
A165: 46097 | B165: PGA Tour | C165: Valspar Championship | D165: Innisbrook Resort (Copperhead Course) | E165: Course Copperhead, Innisbrook Resort, Palm Harbor, Florida Length 7,352 yards Par 71 Course make up Four par-fives; nine par-fours; five par-threes Course type Parkland Grass type Fairways: Celebration Bermudagrass overseeded with Ryegrass; Rough: Celebration Bermudagrass overseeded with Ryegrass 3.75″; Greens: 5,822 sq.ft average featuring TifEagle Bermudagrass with Poa Trivialis overseed; Tournament Stimp: 12ft. Course overview This is a tough, tree-lined layout, with thick rough, hosting for the 25th time (there was no tournament in 2001 or 2020). The event was formerly known as the Tampa Bay Classic, Chrysler Championship, PODS Championship, Transitions Championship and Tampa Bay Championship. What will it take to win the Valspar? Straight hitting and churning out greens in regulation on a tight course with lots of doglegs is the key to success, which is why players such as KJ Choi, Retief Goosen, Jim Furyk, Kevin Streelman, John Senden and Adam Hadwin have flourished in the past. | F165: William Mouw | G165: Pre | H165: E/W | I165: 100-1 | J165: 1/5 Top 8 | K165: 5 | L165: Bet365 | M165: WD | N165: Void | O165: 5 | P165: =SUM(O165-K165) -> 0 | Q165: Matt Fitzpatrick | R165: 12-1 | S165: - Accuracy is key round here, looking for strong APP GIR% - Dry, sunny conditions. Windy on Thursday, calm rest of the week. - [x] Xander, had a tournament low round of 66 in R4. Finished T3 at the players, where he was 1st APP and T5 GIR%. Looks back to his best and a dangerous threat around a course that should suit. - [ ] Ricky Castillo - [ ] Bridgeman - [ ] Hisatsune - [x] William Mouw - [x] Justin Thomas | T165: Pending
A166: 46097 | B166: PGA Tour | C166: Valspar Championship | D166: Innisbrook Resort (Copperhead Course) | E166: Course Copperhead, Innisbrook Resort, Palm Harbor, Florida Length 7,352 yards Par 71 Course make up Four par-fives; nine par-fours; five par-threes Course type Parkland Grass type Fairways: Celebration Bermudagrass overseeded with Ryegrass; Rough: Celebration Bermudagrass overseeded with Ryegrass 3.75″; Greens: 5,822 sq.ft average featuring TifEagle Bermudagrass with Poa Trivialis overseed; Tournament Stimp: 12ft. Course overview This is a tough, tree-lined layout, with thick rough, hosting for the 25th time (there was no tournament in 2001 or 2020). The event was formerly known as the Tampa Bay Classic, Chrysler Championship, PODS Championship, Transitions Championship and Tampa Bay Championship. What will it take to win the Valspar? Straight hitting and churning out greens in regulation on a tight course with lots of doglegs is the key to success, which is why players such as KJ Choi, Retief Goosen, Jim Furyk, Kevin Streelman, John Senden and Adam Hadwin have flourished in the past. | F166: Xander Schauffele | G166: Pre | H166: Outright | I166: 13-1 | J166: N/A | K166: 15 | L166: Bet365 | M166: T4 | N166: Loss | O166: 0 | P166: =SUM(O166-K166) -> -15 | Q166: Matt Fitzpatrick | R166: 12-1 | S166: - Accuracy is key round here, looking for strong APP GIR% - Dry, sunny conditions. Windy on Thursday, calm rest of the week. - [x] Xander, had a tournament low round of 66 in R4. Finished T3 at the players, where he was 1st APP and T5 GIR%. Looks back to his best and a dangerous threat around a course that should suit. - [ ] Ricky Castillo - [ ] Bridgeman - [ ] Hisatsune - [x] William Mouw - [x] Justin Thomas | T166: Pending
A167: 46097 | B167: PGA Tour | C167: THE PLAYERS Championship | D167: TPC Sawgrass (THE PLAYERS Stadium Course) | E167: Course Stadium Course, TPC Sawgrass, Ponte Vedra Beach, Florida Length 7,352 yards Par 72 Course make up Four par-five holes; ten par-fours; four par-threes Course type Parkland Grass type Fairways: Celebration Bermudagrass overseeded with Champion Fine Ryegrass; Rough: Celebration Bermudagrass overseeded with Champion Fine Ryegrass 4″; Greens: 5,500 sq.ft. average TifEagle Bermuda overseeded with Poa Trivialis; Tournament Stimp: 12.5ft. Course overview This Pete Dye design has hosted the tournament since 1982. The island-green 17th is one of the most famous holes in golf. The switch in 2019 from a May date to a March one made for lusher conditions so the ball does not roll to the same extent. Longer clubs are required on approach, but the small, contoured greens are more receptive. The 2020 event was cancelled after one round due to Covid. What will it take to win the Players Championship? Plodders traditionally succeeded at this venue in May, but the switch to March effectively lengthened the track and played into the hands of big-hitters. Given a breezy first two rounds are forecast - and the amount of water in play - accuracy still trumps power | F167: Matt Fitzpatrick | G167: Pre | H167: First Round Leader E/W | I167: 40-1 | J167: 1/4 Top 5 | K167: 2.5 | L167: SkyBet | M167: N/A | N167: Loss | O167: 0 | P167: =SUM(O167-K167) -> -2.5 | Q167: Cameron Young | R167: 30-1 | S167: - Trends: - 14 in the last 17 winners had a AM/PM tee split, Rory has PM/AM last year. - The last 14 Sawgrass champions finished in the top 35 in their preceding tournament. - The last 6 winners ranked top10 in the world rankings: 2025: Mcilroy 2; 2024: Scheffler 1; 2023: Scheffler 2; 2022: Smith 10; 2021: Thomas 3; 2019: McIlroy 6. - 4 in the last 6 winners ranked 1st T2G - 5/5 ranked top 10 APP - 4/5 ranked outside top 35 putting, the other was Cam Smith 2022 ranking 1st - Experience needed, only 1 past champion in 30/40 years has won as a rookie. - A focus on T2G, OTT & APP - It does seem to have a big emphasis on driving distance. - Small chance of rain on Thursday, wind seems to be up on Thursday gusting upto 20mph. Otherwise fairly calm for the week. - [x] Collin Morikawa catches my eye and seems to fit into the trends above. For last three months he ranks 3rd T2G, 5th APP which bodes well here. Decent 5th place at Bay Hill last week, 7th APP, 9th OTT and interestingly 13th Putt which is good for him. T10 here last year with T13 2023. - [x] Min Woo Lee arguably playing the best golf of his career to date. T2 at Pebble, T12 at Riviera (includes a poor 3rd round), T6 at Bay Hill last week where I didn’t think it would suit his game. For last three months he ranks 6th OTT, 26th PUTT. T6 here in 2023, T20 last year. - [x] Adam Scott is having a fantastic year, regularly featuring in some big leaderboards. 4th at Riv which included two 63s, T11 at Bay Hill this last week, 12th APP, 11th Putt. Been here plenty of times - [ ] Viktor - [x] Matti Schmid - [ ] Joel Dahmen | T167: Cameron Young bold finish to see off Matt Fitz was not what how I expected this tournament to end. From Thursday to mid Sunday it was the Ludvig show, until he dumped two balls in the water on 11 & 12 out of nowhere. This was where a charging Fitz and Young stormed into the lead, both making fantastic putts and hitting bold shots, Young with a great birdie on 17 setup a tie for the lead going down 18 and then an incredible 375 yard drive down the 18 set up a simple par finish which beat Fitzy’s bogey. A great tournament with a finish to match. Course was on point this year, playing firm and fast with some naughty run offs, rough very pineal. Young seemed to fit all the trends again, apart from 1 which is the top10 OWGR ranking, however if you look at the data golf rankings he does fit the trend for top10 winners… a note to take for next year. Eye Catchers - Xander looking back to his best warming up nicely for the Masters. Rookie Yellamaraju looks like a great prospect fresh off the Korn Ferry tour.
A168: 46093 | B168: PGA Tour | C168: THE PLAYERS Championship | D168: TPC Sawgrass (THE PLAYERS Stadium Course) | E168: Course Stadium Course, TPC Sawgrass, Ponte Vedra Beach, Florida Length 7,352 yards Par 72 Course make up Four par-five holes; ten par-fours; four par-threes Course type Parkland Grass type Fairways: Celebration Bermudagrass overseeded with Champion Fine Ryegrass; Rough: Celebration Bermudagrass overseeded with Champion Fine Ryegrass 4″; Greens: 5,500 sq.ft. average TifEagle Bermuda overseeded with Poa Trivialis; Tournament Stimp: 12.5ft. Course overview This Pete Dye design has hosted the tournament since 1982. The island-green 17th is one of the most famous holes in golf. The switch in 2019 from a May date to a March one made for lusher conditions so the ball does not roll to the same extent. Longer clubs are required on approach, but the small, contoured greens are more receptive. The 2020 event was cancelled after one round due to Covid. What will it take to win the Players Championship? Plodders traditionally succeeded at this venue in May, but the switch to March effectively lengthened the track and played into the hands of big-hitters. Given a breezy first two rounds are forecast - and the amount of water in play - accuracy still trumps power | F168: Kristoffer Reitan | G168: Pre | H168: First Round Leader E/W | I168: 100-1 | J168: 1/4 Top 5 | K168: 2.5 | L168: SkyBet | M168: N/A | N168: Loss | O168: 0 | P168: =SUM(O168-K168) -> -2.5 | Q168: Cameron Young | R168: 30-1 | S168: - Trends: - 14 in the last 17 winners had a AM/PM tee split, Rory has PM/AM last year. - The last 14 Sawgrass champions finished in the top 35 in their preceding tournament. - The last 6 winners ranked top10 in the world rankings: 2025: Mcilroy 2; 2024: Scheffler 1; 2023: Scheffler 2; 2022: Smith 10; 2021: Thomas 3; 2019: McIlroy 6. - 4 in the last 6 winners ranked 1st T2G - 5/5 ranked top 10 APP - 4/5 ranked outside top 35 putting, the other was Cam Smith 2022 ranking 1st - Experience needed, only 1 past champion in 30/40 years has won as a rookie. - A focus on T2G, OTT & APP - It does seem to have a big emphasis on driving distance. - Small chance of rain on Thursday, wind seems to be up on Thursday gusting upto 20mph. Otherwise fairly calm for the week. - [x] Collin Morikawa catches my eye and seems to fit into the trends above. For last three months he ranks 3rd T2G, 5th APP which bodes well here. Decent 5th place at Bay Hill last week, 7th APP, 9th OTT and interestingly 13th Putt which is good for him. T10 here last year with T13 2023. - [x] Min Woo Lee arguably playing the best golf of his career to date. T2 at Pebble, T12 at Riviera (includes a poor 3rd round), T6 at Bay Hill last week where I didn’t think it would suit his game. For last three months he ranks 6th OTT, 26th PUTT. T6 here in 2023, T20 last year. - [x] Adam Scott is having a fantastic year, regularly featuring in some big leaderboards. 4th at Riv which included two 63s, T11 at Bay Hill this last week, 12th APP, 11th Putt. Been here plenty of times - [ ] Viktor - [x] Matti Schmid - [ ] Joel Dahmen | T168: Cameron Young bold finish to see off Matt Fitz was not what how I expected this tournament to end. From Thursday to mid Sunday it was the Ludvig show, until he dumped two balls in the water on 11 & 12 out of nowhere. This was where a charging Fitz and Young stormed into the lead, both making fantastic putts and hitting bold shots, Young with a great birdie on 17 setup a tie for the lead going down 18 and then an incredible 375 yard drive down the 18 set up a simple par finish which beat Fitzy’s bogey. A great tournament with a finish to match. Course was on point this year, playing firm and fast with some naughty run offs, rough very pineal. Young seemed to fit all the trends again, apart from 1 which is the top10 OWGR ranking, however if you look at the data golf rankings he does fit the trend for top10 winners… a note to take for next year. Eye Catchers - Xander looking back to his best warming up nicely for the Masters. Rookie Yellamaraju looks like a great prospect fresh off the Korn Ferry tour.
A169: 46093 | B169: PGA Tour | C169: THE PLAYERS Championship | D169: TPC Sawgrass (THE PLAYERS Stadium Course) | E169: Course Stadium Course, TPC Sawgrass, Ponte Vedra Beach, Florida Length 7,352 yards Par 72 Course make up Four par-five holes; ten par-fours; four par-threes Course type Parkland Grass type Fairways: Celebration Bermudagrass overseeded with Champion Fine Ryegrass; Rough: Celebration Bermudagrass overseeded with Champion Fine Ryegrass 4″; Greens: 5,500 sq.ft. average TifEagle Bermuda overseeded with Poa Trivialis; Tournament Stimp: 12.5ft. Course overview This Pete Dye design has hosted the tournament since 1982. The island-green 17th is one of the most famous holes in golf. The switch in 2019 from a May date to a March one made for lusher conditions so the ball does not roll to the same extent. Longer clubs are required on approach, but the small, contoured greens are more receptive. The 2020 event was cancelled after one round due to Covid. What will it take to win the Players Championship? Plodders traditionally succeeded at this venue in May, but the switch to March effectively lengthened the track and played into the hands of big-hitters. Given a breezy first two rounds are forecast - and the amount of water in play - accuracy still trumps power | F169: Collin Morikawa | G169: Pre | H169: First Round Leader E/W | I169: 28-1 | J169: 1/4 Top 5 | K169: 5 | L169: Bet365 | M169: WD | N169: Void | O169: 5 | P169: =SUM(O169-K169) -> 0 | Q169: Cameron Young | R169: 30-1 | S169: - Trends: - 14 in the last 17 winners had a AM/PM tee split, Rory has PM/AM last year. - The last 14 Sawgrass champions finished in the top 35 in their preceding tournament. - The last 6 winners ranked top10 in the world rankings: 2025: Mcilroy 2; 2024: Scheffler 1; 2023: Scheffler 2; 2022: Smith 10; 2021: Thomas 3; 2019: McIlroy 6. - 4 in the last 6 winners ranked 1st T2G - 5/5 ranked top 10 APP - 4/5 ranked outside top 35 putting, the other was Cam Smith 2022 ranking 1st - Experience needed, only 1 past champion in 30/40 years has won as a rookie. - A focus on T2G, OTT & APP - It does seem to have a big emphasis on driving distance. - Small chance of rain on Thursday, wind seems to be up on Thursday gusting upto 20mph. Otherwise fairly calm for the week. - [x] Collin Morikawa catches my eye and seems to fit into the trends above. For last three months he ranks 3rd T2G, 5th APP which bodes well here. Decent 5th place at Bay Hill last week, 7th APP, 9th OTT and interestingly 13th Putt which is good for him. T10 here last year with T13 2023. - [x] Min Woo Lee arguably playing the best golf of his career to date. T2 at Pebble, T12 at Riviera (includes a poor 3rd round), T6 at Bay Hill last week where I didn’t think it would suit his game. For last three months he ranks 6th OTT, 26th PUTT. T6 here in 2023, T20 last year. - [x] Adam Scott is having a fantastic year, regularly featuring in some big leaderboards. 4th at Riv which included two 63s, T11 at Bay Hill this last week, 12th APP, 11th Putt. Been here plenty of times - [ ] Viktor - [x] Matti Schmid - [ ] Joel Dahmen | T169: Cameron Young bold finish to see off Matt Fitz was not what how I expected this tournament to end. From Thursday to mid Sunday it was the Ludvig show, until he dumped two balls in the water on 11 & 12 out of nowhere. This was where a charging Fitz and Young stormed into the lead, both making fantastic putts and hitting bold shots, Young with a great birdie on 17 setup a tie for the lead going down 18 and then an incredible 375 yard drive down the 18 set up a simple par finish which beat Fitzy’s bogey. A great tournament with a finish to match. Course was on point this year, playing firm and fast with some naughty run offs, rough very pineal. Young seemed to fit all the trends again, apart from 1 which is the top10 OWGR ranking, however if you look at the data golf rankings he does fit the trend for top10 winners… a note to take for next year. Eye Catchers - Xander looking back to his best warming up nicely for the Masters. Rookie Yellamaraju looks like a great prospect fresh off the Korn Ferry tour.
A170: 46093 | B170: PGA Tour | C170: THE PLAYERS Championship | D170: TPC Sawgrass (THE PLAYERS Stadium Course) | E170: Course Stadium Course, TPC Sawgrass, Ponte Vedra Beach, Florida Length 7,352 yards Par 72 Course make up Four par-five holes; ten par-fours; four par-threes Course type Parkland Grass type Fairways: Celebration Bermudagrass overseeded with Champion Fine Ryegrass; Rough: Celebration Bermudagrass overseeded with Champion Fine Ryegrass 4″; Greens: 5,500 sq.ft. average TifEagle Bermuda overseeded with Poa Trivialis; Tournament Stimp: 12.5ft. Course overview This Pete Dye design has hosted the tournament since 1982. The island-green 17th is one of the most famous holes in golf. The switch in 2019 from a May date to a March one made for lusher conditions so the ball does not roll to the same extent. Longer clubs are required on approach, but the small, contoured greens are more receptive. The 2020 event was cancelled after one round due to Covid. What will it take to win the Players Championship? Plodders traditionally succeeded at this venue in May, but the switch to March effectively lengthened the track and played into the hands of big-hitters. Given a breezy first two rounds are forecast - and the amount of water in play - accuracy still trumps power | F170: Matti Schmid | G170: Pre | H170: E/W | I170: 225-1 | J170: 1/5 Top 12 | K170: 2.5 | L170: Bet365 | M170: T46 | N170: Loss | O170: 0 | P170: =SUM(O170-K170) -> -2.5 | Q170: Cameron Young | R170: 30-1 | S170: - Trends: - 14 in the last 17 winners had a AM/PM tee split, Rory has PM/AM last year. - The last 14 Sawgrass champions finished in the top 35 in their preceding tournament. - The last 6 winners ranked top10 in the world rankings: 2025: Mcilroy 2; 2024: Scheffler 1; 2023: Scheffler 2; 2022: Smith 10; 2021: Thomas 3; 2019: McIlroy 6. - 4 in the last 6 winners ranked 1st T2G - 5/5 ranked top 10 APP - 4/5 ranked outside top 35 putting, the other was Cam Smith 2022 ranking 1st - Experience needed, only 1 past champion in 30/40 years has won as a rookie. - A focus on T2G, OTT & APP - It does seem to have a big emphasis on driving distance. - Small chance of rain on Thursday, wind seems to be up on Thursday gusting upto 20mph. Otherwise fairly calm for the week. - [x] Collin Morikawa catches my eye and seems to fit into the trends above. For last three months he ranks 3rd T2G, 5th APP which bodes well here. Decent 5th place at Bay Hill last week, 7th APP, 9th OTT and interestingly 13th Putt which is good for him. T10 here last year with T13 2023. - [x] Min Woo Lee arguably playing the best golf of his career to date. T2 at Pebble, T12 at Riviera (includes a poor 3rd round), T6 at Bay Hill last week where I didn’t think it would suit his game. For last three months he ranks 6th OTT, 26th PUTT. T6 here in 2023, T20 last year. - [x] Adam Scott is having a fantastic year, regularly featuring in some big leaderboards. 4th at Riv which included two 63s, T11 at Bay Hill this last week, 12th APP, 11th Putt. Been here plenty of times - [ ] Viktor - [x] Matti Schmid - [ ] Joel Dahmen | T170: Cameron Young bold finish to see off Matt Fitz was not what how I expected this tournament to end. From Thursday to mid Sunday it was the Ludvig show, until he dumped two balls in the water on 11 & 12 out of nowhere. This was where a charging Fitz and Young stormed into the lead, both making fantastic putts and hitting bold shots, Young with a great birdie on 17 setup a tie for the lead going down 18 and then an incredible 375 yard drive down the 18 set up a simple par finish which beat Fitzy’s bogey. A great tournament with a finish to match. Course was on point this year, playing firm and fast with some naughty run offs, rough very pineal. Young seemed to fit all the trends again, apart from 1 which is the top10 OWGR ranking, however if you look at the data golf rankings he does fit the trend for top10 winners… a note to take for next year. Eye Catchers - Xander looking back to his best warming up nicely for the Masters. Rookie Yellamaraju looks like a great prospect fresh off the Korn Ferry tour.
A171: 46090 | B171: PGA Tour | C171: THE PLAYERS Championship | D171: TPC Sawgrass (THE PLAYERS Stadium Course) | E171: Course Stadium Course, TPC Sawgrass, Ponte Vedra Beach, Florida Length 7,352 yards Par 72 Course make up Four par-five holes; ten par-fours; four par-threes Course type Parkland Grass type Fairways: Celebration Bermudagrass overseeded with Champion Fine Ryegrass; Rough: Celebration Bermudagrass overseeded with Champion Fine Ryegrass 4″; Greens: 5,500 sq.ft. average TifEagle Bermuda overseeded with Poa Trivialis; Tournament Stimp: 12.5ft. Course overview This Pete Dye design has hosted the tournament since 1982. The island-green 17th is one of the most famous holes in golf. The switch in 2019 from a May date to a March one made for lusher conditions so the ball does not roll to the same extent. Longer clubs are required on approach, but the small, contoured greens are more receptive. The 2020 event was cancelled after one round due to Covid. What will it take to win the Players Championship? Plodders traditionally succeeded at this venue in May, but the switch to March effectively lengthened the track and played into the hands of big-hitters. Given a breezy first two rounds are forecast - and the amount of water in play - accuracy still trumps power | F171: Si Woo Kim | G171: Pre | H171: E/W | I171: 30-1 | J171: 1/5 Top 8 | K171: 15 | L171: SkyBet | M171: T50 | N171: Loss | O171: 0 | P171: =SUM(O171-K171) -> -15 | Q171: Cameron Young | R171: 30-1 | S171: - Trends: - 14 in the last 17 winners had a AM/PM tee split, Rory has PM/AM last year. - The last 14 Sawgrass champions finished in the top 35 in their preceding tournament. - The last 6 winners ranked top10 in the world rankings: 2025: Mcilroy 2; 2024: Scheffler 1; 2023: Scheffler 2; 2022: Smith 10; 2021: Thomas 3; 2019: McIlroy 6. - 4 in the last 6 winners ranked 1st T2G - 5/5 ranked top 10 APP - 4/5 ranked outside top 35 putting, the other was Cam Smith 2022 ranking 1st - Experience needed, only 1 past champion in 30/40 years has won as a rookie. - A focus on T2G, OTT & APP - It does seem to have a big emphasis on driving distance. - Small chance of rain on Thursday, wind seems to be up on Thursday gusting upto 20mph. Otherwise fairly calm for the week. - [x] Collin Morikawa catches my eye and seems to fit into the trends above. For last three months he ranks 3rd T2G, 5th APP which bodes well here. Decent 5th place at Bay Hill last week, 7th APP, 9th OTT and interestingly 13th Putt which is good for him. T10 here last year with T13 2023. - [x] Min Woo Lee arguably playing the best golf of his career to date. T2 at Pebble, T12 at Riviera (includes a poor 3rd round), T6 at Bay Hill last week where I didn’t think it would suit his game. For last three months he ranks 6th OTT, 26th PUTT. T6 here in 2023, T20 last year. - [x] Adam Scott is having a fantastic year, regularly featuring in some big leaderboards. 4th at Riv which included two 63s, T11 at Bay Hill this last week, 12th APP, 11th Putt. Been here plenty of times - [ ] Viktor - [x] Matti Schmid - [ ] Joel Dahmen | T171: Cameron Young bold finish to see off Matt Fitz was not what how I expected this tournament to end. From Thursday to mid Sunday it was the Ludvig show, until he dumped two balls in the water on 11 & 12 out of nowhere. This was where a charging Fitz and Young stormed into the lead, both making fantastic putts and hitting bold shots, Young with a great birdie on 17 setup a tie for the lead going down 18 and then an incredible 375 yard drive down the 18 set up a simple par finish which beat Fitzy’s bogey. A great tournament with a finish to match. Course was on point this year, playing firm and fast with some naughty run offs, rough very pineal. Young seemed to fit all the trends again, apart from 1 which is the top10 OWGR ranking, however if you look at the data golf rankings he does fit the trend for top10 winners… a note to take for next year. Eye Catchers - Xander looking back to his best warming up nicely for the Masters. Rookie Yellamaraju looks like a great prospect fresh off the Korn Ferry tour.
... A174: 46090 | B174: PGA Tour | C174: THE PLAYERS Championship | D174: TPC Sawgrass (THE PLAYERS Stadium Course) | E174: Course Stadium Course, TPC Sawgrass, Ponte Vedra Beach, Florida Length 7,352 yards Par 72 Course make up Four par-five holes; ten par-fours; four par-threes Course type Parkland Grass type Fairways: Celebration Bermudagrass overseeded with Champion Fine Ryegrass; Rough: Celebration Bermudagrass overseeded with Champion Fine Ryegrass 4″; Greens: 5,500 sq.ft. average TifEagle Bermuda overseeded with Poa Trivialis; Tournament Stimp: 12.5ft. Course overview This Pete Dye design has hosted the tournament since 1982. The island-green 17th is one of the most famous holes in golf. The switch in 2019 from a May date to a March one made for lusher conditions so the ball does not roll to the same extent. Longer clubs are required on approach, but the small, contoured greens are more receptive. The 2020 event was cancelled after one round due to Covid. What will it take to win the Players Championship? Plodders traditionally succeeded at this venue in May, but the switch to March effectively lengthened the track and played into the hands of big-hitters. Given a breezy first two rounds are forecast - and the amount of water in play - accuracy still trumps power | F174: Min Woo Lee | G174: Pre | H174: E/W | I174: 40-1 | J174: 1/5 Top 8 | K174: 10 | L174: SkyBet | M174: T32 | N174: Loss | O174: 0 | P174: =SUM(O174-K174) -> -10 | Q174: Cameron Young | R174: 30-1 | S174: - Trends: - 14 in the last 17 winners had a AM/PM tee split, Rory has PM/AM last year. - The last 14 Sawgrass champions finished in the top 35 in their preceding tournament. - The last 6 winners ranked top10 in the world rankings: 2025: Mcilroy 2; 2024: Scheffler 1; 2023: Scheffler 2; 2022: Smith 10; 2021: Thomas 3; 2019: McIlroy 6. - 4 in the last 6 winners ranked 1st T2G - 5/5 ranked top 10 APP - 4/5 ranked outside top 35 putting, the other was Cam Smith 2022 ranking 1st - Experience needed, only 1 past champion in 30/40 years has won as a rookie. - A focus on T2G, OTT & APP - It does seem to have a big emphasis on driving distance. - Small chance of rain on Thursday, wind seems to be up on Thursday gusting upto 20mph. Otherwise fairly calm for the week. - [x] Collin Morikawa catches my eye and seems to fit into the trends above. For last three months he ranks 3rd T2G, 5th APP which bodes well here. Decent 5th place at Bay Hill last week, 7th APP, 9th OTT and interestingly 13th Putt which is good for him. T10 here last year with T13 2023. - [x] Min Woo Lee arguably playing the best golf of his career to date. T2 at Pebble, T12 at Riviera (includes a poor 3rd round), T6 at Bay Hill last week where I didn’t think it would suit his game. For last three months he ranks 6th OTT, 26th PUTT. T6 here in 2023, T20 last year. - [x] Adam Scott is having a fantastic year, regularly featuring in some big leaderboards. 4th at Riv which included two 63s, T11 at Bay Hill this last week, 12th APP, 11th Putt. Been here plenty of times - [ ] Viktor - [x] Matti Schmid - [ ] Joel Dahmen | T174: Cameron Young bold finish to see off Matt Fitz was not what how I expected this tournament to end. From Thursday to mid Sunday it was the Ludvig show, until he dumped two balls in the water on 11 & 12 out of nowhere. This was where a charging Fitz and Young stormed into the lead, both making fantastic putts and hitting bold shots, Young with a great birdie on 17 setup a tie for the lead going down 18 and then an incredible 375 yard drive down the 18 set up a simple par finish which beat Fitzy’s bogey. A great tournament with a finish to match. Course was on point this year, playing firm and fast with some naughty run offs, rough very pineal. Young seemed to fit all the trends again, apart from 1 which is the top10 OWGR ranking, however if you look at the data golf rankings he does fit the trend for top10 winners… a note to take for next year. Eye Catchers - Xander looking back to his best warming up nicely for the Masters. Rookie Yellamaraju looks like a great prospect fresh off the Korn Ferry tour.
A175: 46090 | B175: N/A | C175: Arnold Palmer Invitational / Joburg Open | D175: N/A | F175: Scottie Scheffler / Jayden Schaper | G175: Pre | H175: Double | I175: 16-1 | J175: 1/4 Top 5 | K175: 5 | L175: Bet365 | M175: N/A | N175: Loss | O175: 0 | P175: =SUM(O175-K175) -> -5 | Q175: N/A | R175: N/A | S175: N/A | T175: N/A
A176: 46085 | B176: PGA Tour | C176: Arnold Palmer Invitational | D176: Bay Hill | E176: Course Arnold Palmer's Bay Hill Club and Lodge, Orlando, Florida Length 7,466 yards Par 72 Course make up Four par-five holes; ten par-fours; four par-threes Course type Parkland Grass type Fairways: Celebration Bermuda overseeded with Perennial Rye; Rough: Celebration Bermuda overseeded with Perennial Rye 3″; Greens: 7,500 sq.ft average TifEagle Bermudagrass; Tournament Stimp: 12ft. Course overview Bay Hill has hosted a PGA Tour event every year since 1979. Arnold Palmer made significant changes to the track before the 2010 edition, so form before then is of little relevance. Water is in play on several holes and there are lots of doglegs. The Arnold Palmer has been a Signature Event since 2023. What will it take to win the Arnold Palmer Invitational? There is plenty of water to trouble the competitors on this tough layout, as well as greenside run-off areas, putting a premium on accuracy and the ability to grind pars. | F176: Rory Mcilroy | G176: Pre | H176: First Round Leader E/W | I176: 16-1 | J176: 1/4 Top 5 | K176: 5 | L176: Bet365 | M176: N/A | N176: Loss | O176: 0 | P176: =SUM(O176-K176) -> -5 | Q176: Akshay Bhatia | R176: 70-1 | S176: - Looking for strong ball strikers, last year this was firm and fast and you really wanted to be accurate and excel in GIR. - Bay Hill is relitively long but main difficulty is the firmness of the course and getting the ball to stop. - [x] Kurt Kityama form can be patchy but each year seems to have a purple patch or two where he picks up top 10s and a win. He won this back in 2023 on debut, with a 2nd at Riv in his last start on tough greens, if he can putt like that this week he could get himself right in the mix. - [x] Sepp Straka has had a quiet start to this season, most likely trying to find some form after dealing with some difficult personal matters off the course last year. He’s always been a top quality ball striker and straight off the tee, T5 last year and his game should suit round here. At a big price for him he could go well this week. - [x] Rory Mcilroy holds the best scoring record round here for the last ten year by some margin. Arguably should have won at Riv on his last start but the putter let him down over the weekend, which as of late is unusual as he’s become a top putter. I think the change back to bermudagrass will help him this week, as long as the T2G is still strong he could have a massive chance this week to pick up a second Arnold Palmer invitational. | T176: Bay Hill played firm and fast as expected, Daniel Berger was seemingly on his way to a wire-to-wire win until he was pipped on the last hole by Akshay Bhatia to force a playoff down 18 which Akshay won. Akshay was holing putts from all over the place especially on the back 9. An incredible eagle on the 16th put him right in contention and played the 18th impressively whereas Berger did not bogeying the hole in regulation and the playoff. Rory WD prior to the 3rd round with a tweak in his back, Sepp was right in the mix on Sunday but really disappointed on the back 9 with a string of bogies. Kurt midway back. Eye Catchers - Min Woo Lee continues to impress on courses you wouldn’t think he we would excel on. Morikawa looks back to his best.
A177: 46085 | B177: PGA Tour | C177: Arnold Palmer Invitational | D177: Bay Hill | E177: Course Arnold Palmer's Bay Hill Club and Lodge, Orlando, Florida Length 7,466 yards Par 72 Course make up Four par-five holes; ten par-fours; four par-threes Course type Parkland Grass type Fairways: Celebration Bermuda overseeded with Perennial Rye; Rough: Celebration Bermuda overseeded with Perennial Rye 3″; Greens: 7,500 sq.ft average TifEagle Bermudagrass; Tournament Stimp: 12ft. Course overview Bay Hill has hosted a PGA Tour event every year since 1979. Arnold Palmer made significant changes to the track before the 2010 edition, so form before then is of little relevance. Water is in play on several holes and there are lots of doglegs. The Arnold Palmer has been a Signature Event since 2023. What will it take to win the Arnold Palmer Invitational? There is plenty of water to trouble the competitors on this tough layout, as well as greenside run-off areas, putting a premium on accuracy and the ability to grind pars. | F177: Rory Mcilroy | G177: Pre | H177: Outright | I177: 11-1 | J177: N/A | K177: 15 | L177: SkyBet | M177: WD | N177: Loss | O177: 0 | P177: =SUM(O177-K177) -> -15 | Q177: Akshay Bhatia | R177: 70-1 | S177: - Looking for strong ball strikers, last year this was firm and fast and you really wanted to be accurate and excel in GIR. - Bay Hill is relitively long but main difficulty is the firmness of the course and getting the ball to stop. - [x] Kurt Kityama form can be patchy but each year seems to have a purple patch or two where he picks up top 10s and a win. He won this back in 2023 on debut, with a 2nd at Riv in his last start on tough greens, if he can putt like that this week he could get himself right in the mix. - [x] Sepp Straka has had a quiet start to this season, most likely trying to find some form after dealing with some difficult personal matters off the course last year. He’s always been a top quality ball striker and straight off the tee, T5 last year and his game should suit round here. At a big price for him he could go well this week. - [x] Rory Mcilroy holds the best scoring record round here for the last ten year by some margin. Arguably should have won at Riv on his last start but the putter let him down over the weekend, which as of late is unusual as he’s become a top putter. I think the change back to bermudagrass will help him this week, as long as the T2G is still strong he could have a massive chance this week to pick up a second Arnold Palmer invitational. | T177: Bay Hill played firm and fast as expected, Daniel Berger was seemingly on his way to a wire-to-wire win until he was pipped on the last hole by Akshay Bhatia to force a playoff down 18 which Akshay won. Akshay was holing putts from all over the place especially on the back 9. An incredible eagle on the 16th put him right in contention and played the 18th impressively whereas Berger did not bogeying the hole in regulation and the playoff. Rory WD prior to the 3rd round with a tweak in his back, Sepp was right in the mix on Sunday but really disappointed on the back 9 with a string of bogies. Kurt midway back. Eye Catchers - Min Woo Lee continues to impress on courses you wouldn’t think he we would excel on. Morikawa looks back to his best.
A178: 46083 | B178: PGA Tour | C178: Puerto Rico Open | D178: Grand Reserve Golf Club | E178: Course Grand Reserve Golf Club, Rio Grande, Puerto Rico Length 7,506 yards Par 72 Course make up Four par-five holes; ten par-fours; four par-threes Course type Parkland Grass type Fairways: Celebration Bermuda overseeded with Perennial Rye; Rough: Celebration Bermuda overseeded with Perennial Rye 3″; Greens: 7,500 sq.ft average TifEagle Bermudagrass; Tournament Stimp: 12ft. Course overview This Tom Kite layout has hosted the Puerto Rico Open since 2008, with various name changes through the years (Trump International, Coco Beach GC). It is flat and has paspalum grass. What will it take to win the Puerto Rico Open? With Ryan Brehm and Brice Garnett, one of the longest drivers in the world and one of the shortest, on the honours board in two of the last four years, there is clearly more than one way to succeed at Grand Reserve. Accuracy will count for more this week with a wind blowing throughout. | F178: Ricky Castillo | G178: Pre | H178: E/W | I178: 28-1 | J178: 1/5 Top 7 | K178: 10 | L178: Coral | M178: 1 | N178: Win | O178: 178 | P178: =SUM(O178-K178) -> 168 | Q178: Ricky Castillo | R178: 20-1 | S178: - Looking for good ball strikers. Likely to be windy in Puerto Rico gusting upto 20mph on each day. - [x] Ricky Castillo looked impressive last week at PGA National finishing 5th despite a fairly slow start. T64 here last year so he knows the place and in this weak field could come out on top for a maiden PGA tour win. | T178: I didn’t watch any of this as it was not broadcasted in the UK, however very happy my only pick Ricky Castillo prevailed on Sunday. The 25 yo is an upcoming talent, narrowly missing out on his tour card last year he is back more determined than ever. This win will provide exemption for the next two years and the shackles are off for him to really make his mark on the PGA tour. Former world no1 amateur lets not forget, he has the game and talent to go really far.
A179: 46083 | B179: DP World Tour | C179: Joburg Open | D179: Houghton GC | E179: Course Houghton Golf Club, Johannesburg, South Africa Length 7,241 yards Par 70 Course make-up Two par-five holes; 12 par-fours; four par-threes Course type Parkland Grass type Greens are undulating Bentgrass Course Overview AM Copeland designed this classic track, which was opened in 1926, and it staged the South African Open eight times between 1951 and 1992. The South African PGA was played there from 1993 through 1999. And from 2000 through 2004, Houghton was the venue for the Alfred Dunhill Championship on the European Tour. The course was then sold, though, and completely changed by Jack Nicklaus and his team, opening in 2009. The only significant course form since the redesign is the Sunshine Tour Qualifying School in 2019 and 2020, and the Joburg Opens in 2022, 2023 and last year. This is a short track, given it is played at altitude in the Highveld. Heavy bunkering, water hazards and undulating greens are the defence. The par was reduced from 71 to 70 in 2024, with the third hole becoming a par-four, rather than a five. What will it take to win the Joburg Open As with most Nicklaus designs, accurate iron-play is essential to greens heavily guarded by bunkers. | F179: Jacob Skov Olesen | G179: Pre | H179: E/W | I179: 45-1 | J179: 1/5 Top 8 | K179: 7.5 | L179: Bet365 | M179: T36 | N179: Loss | O179: 0 | P179: =SUM(O179-K179) -> -7.5 | Q179: Dan Bradbury | R179: 35-1 | S179: - Weather in Joburg looks mixed, risk of thundery showers Thurs-Sat and then windy on Sunday gusting upto 25mph. - Relatively short course with the altitude factored in. Nicklaus redesigned with plenty of bunkers guarding greens. Looking for strong ball strikers and T2G, want to be playing second shots from FW. - [x] Daniel Van Tonder has a great record here, T3, CUT, 5 on his last three goes. As like many SA players, comes alive in his home country. T6 last week at Stellenbosch indicates his game is back to its best after a few poor week prior. Should go well this week. - [x] Jacob Scov Olesen is an old favourite of mine, picking up plenty of place money for me since noticing him as an amateur. Normally I like him on links and/or where it’s going to be windy and wet. According to the forecast we will see the latter. T7 here on debut last year where I was on him and placed, he does seem to like this African stretch and willing to take another punt on him this year. | T179: A typical SA feeling track this week, Houghton GC played at altitude with many SA players rising to the top of the leaderboard. However it was Englishmen Dan Bradbury who came out on top, fending off Casey Jarvis (for his third win in a row), Hennie Du Palsies & Branden RT. Bradbury has a sneakily good record in SA and when the putter is hot, can battle against anyone on the DPWT. Daniel Van Tonder returned a shared place, Jacob Scott Olesen disappointed in the last round with a 74 when not far off contention. Eye Catchers -
A180: 46083 | B180: DP World Tour | C180: Joburg Open | D180: Houghton GC | E180: Course Houghton Golf Club, Johannesburg, South Africa Length 7,241 yards Par 70 Course make-up Two par-five holes; 12 par-fours; four par-threes Course type Parkland Grass type Greens are undulating Bentgrass Course Overview AM Copeland designed this classic track, which was opened in 1926, and it staged the South African Open eight times between 1951 and 1992. The South African PGA was played there from 1993 through 1999. And from 2000 through 2004, Houghton was the venue for the Alfred Dunhill Championship on the European Tour. The course was then sold, though, and completely changed by Jack Nicklaus and his team, opening in 2009. The only significant course form since the redesign is the Sunshine Tour Qualifying School in 2019 and 2020, and the Joburg Opens in 2022, 2023 and last year. This is a short track, given it is played at altitude in the Highveld. Heavy bunkering, water hazards and undulating greens are the defence. The par was reduced from 71 to 70 in 2024, with the third hole becoming a par-four, rather than a five. What will it take to win the Joburg Open As with most Nicklaus designs, accurate iron-play is essential to greens heavily guarded by bunkers. | F180: Daniel Van Tonder | G180: Pre | H180: E/W | I180: 33-1 | J180: 1/5 Top 8 | K180: 10 | L180: Bet365 | M180: T6 | N180: Place | O180: 28.5 | P180: =SUM(O180-K180) -> 18.5 | Q180: Dan Bradbury | R180: 35-1 | S180: - Weather in Joburg looks mixed, risk of thundery showers Thurs-Sat and then windy on Sunday gusting upto 25mph. - Relatively short course with the altitude factored in. Nicklaus redesigned with plenty of bunkers guarding greens. Looking for strong ball strikers and T2G, want to be playing second shots from FW. - [x] Daniel Van Tonder has a great record here, T3, CUT, 5 on his last three goes. As like many SA players, comes alive in his home country. T6 last week at Stellenbosch indicates his game is back to its best after a few poor week prior. Should go well this week. - [x] Jacob Scov Olesen is an old favourite of mine, picking up plenty of place money for me since noticing him as an amateur. Normally I like him on links and/or where it’s going to be windy and wet. According to the forecast we will see the latter. T7 here on debut last year where I was on him and placed, he does seem to like this African stretch and willing to take another punt on him this year. | T180: A typical SA feeling track this week, Houghton GC played at altitude with many SA players rising to the top of the leaderboard. However it was Englishmen Dan Bradbury who came out on top, fending off Casey Jarvis (for his third win in a row), Hennie Du Palsies & Branden RT. Bradbury has a sneakily good record in SA and when the putter is hot, can battle against anyone on the DPWT. Daniel Van Tonder returned a shared place, Jacob Scott Olesen disappointed in the last round with a 74 when not far off contention. Eye Catchers -
A181: 46083 | B181: PGA Tour | C181: Arnold Palmer Invitational | D181: Bay Hill | E181: Course Arnold Palmer's Bay Hill Club and Lodge, Orlando, Florida Length 7,466 yards Par 72 Course make up Four par-five holes; ten par-fours; four par-threes Course type Parkland Grass type Fairways: Celebration Bermuda overseeded with Perennial Rye; Rough: Celebration Bermuda overseeded with Perennial Rye 3″; Greens: 7,500 sq.ft average TifEagle Bermudagrass; Tournament Stimp: 12ft. Course overview Bay Hill has hosted a PGA Tour event every year since 1979. Arnold Palmer made significant changes to the track before the 2010 edition, so form before then is of little relevance. Water is in play on several holes and there are lots of doglegs. The Arnold Palmer has been a Signature Event since 2023. What will it take to win the Arnold Palmer Invitational? There is plenty of water to trouble the competitors on this tough layout, as well as greenside run-off areas, putting a premium on accuracy and the ability to grind pars. | F181: Sepp Straka | G181: Pre | H181: E/W | I181: 55-1 | J181: 1/5 Top 8 | K181: 7.5 | L181: Bet365 | M181: T13 | N181: Place | O181: 0 | P181: =SUM(O181-K181) -> -7.5 | Q181: Akshay Bhatia | R181: 70-1 | S181: - Looking for strong ball strikers, last year this was firm and fast and you really wanted to be accurate and excel in GIR. - Bay Hill is relitively long but main difficulty is the firmness of the course and getting the ball to stop. - [x] Kurt Kityama form can be patchy but each year seems to have a purple patch or two where he picks up top 10s and a win. He won this back in 2023 on debut, with a 2nd at Riv in his last start on tough greens, if he can putt like that this week he could get himself right in the mix. - [x] Sepp Straka has had a quiet start to this season, most likely trying to find some form after dealing with some difficult personal matters off the course last year. He’s always been a top quality ball striker and straight off the tee, T5 last year and his game should suit round here. At a big price for him he could go well this week. - [x] Rory Mcilroy holds the best scoring record round here for the last ten year by some margin. Arguably should have won at Riv on his last start but the putter let him down over the weekend, which as of late is unusual as he’s become a top putter. I think the change back to bermudagrass will help him this week, as long as the T2G is still strong he could have a massive chance this week to pick up a second Arnold Palmer invitational. | T181: Bay Hill played firm and fast as expected, Daniel Berger was seemingly on his way to a wire-to-wire win until he was pipped on the last hole by Akshay Bhatia to force a playoff down 18 which Akshay won. Akshay was holing putts from all over the place especially on the back 9. An incredible eagle on the 16th put him right in contention and played the 18th impressively whereas Berger did not bogeying the hole in regulation and the playoff. Rory WD prior to the 3rd round with a tweak in his back, Sepp was right in the mix on Sunday but really disappointed on the back 9 with a string of bogies. Kurt midway back. Eye Catchers - Min Woo Lee continues to impress on courses you wouldn’t think he we would excel on. Morikawa looks back to his best.
A182: 46083 | B182: PGA Tour | C182: Arnold Palmer Invitational | D182: Bay Hill | E182: Course Arnold Palmer's Bay Hill Club and Lodge, Orlando, Florida Length 7,466 yards Par 72 Course make up Four par-five holes; ten par-fours; four par-threes Course type Parkland Grass type Fairways: Celebration Bermuda overseeded with Perennial Rye; Rough: Celebration Bermuda overseeded with Perennial Rye 3″; Greens: 7,500 sq.ft average TifEagle Bermudagrass; Tournament Stimp: 12ft. Course overview Bay Hill has hosted a PGA Tour event every year since 1979. Arnold Palmer made significant changes to the track before the 2010 edition, so form before then is of little relevance. Water is in play on several holes and there are lots of doglegs. The Arnold Palmer has been a Signature Event since 2023. What will it take to win the Arnold Palmer Invitational? There is plenty of water to trouble the competitors on this tough layout, as well as greenside run-off areas, putting a premium on accuracy and the ability to grind pars. | F182: Kurt Kityama | G182: Pre | H182: E/W | I182: 35-1 | J182: 1/5 Top 8 | K182: 10 | L182: Bet365 | M182: T18 | N182: Loss | O182: 0 | P182: =SUM(O182-K182) -> -10 | Q182: Akshay Bhatia | R182: 70-1 | S182: - Looking for strong ball strikers, last year this was firm and fast and you really wanted to be accurate and excel in GIR. - Bay Hill is relitively long but main difficulty is the firmness of the course and getting the ball to stop. - [x] Kurt Kityama form can be patchy but each year seems to have a purple patch or two where he picks up top 10s and a win. He won this back in 2023 on debut, with a 2nd at Riv in his last start on tough greens, if he can putt like that this week he could get himself right in the mix. - [x] Sepp Straka has had a quiet start to this season, most likely trying to find some form after dealing with some difficult personal matters off the course last year. He’s always been a top quality ball striker and straight off the tee, T5 last year and his game should suit round here. At a big price for him he could go well this week. - [x] Rory Mcilroy holds the best scoring record round here for the last ten year by some margin. Arguably should have won at Riv on his last start but the putter let him down over the weekend, which as of late is unusual as he’s become a top putter. I think the change back to bermudagrass will help him this week, as long as the T2G is still strong he could have a massive chance this week to pick up a second Arnold Palmer invitational. | T182: Bay Hill played firm and fast as expected, Daniel Berger was seemingly on his way to a wire-to-wire win until he was pipped on the last hole by Akshay Bhatia to force a playoff down 18 which Akshay won. Akshay was holing putts from all over the place especially on the back 9. An incredible eagle on the 16th put him right in contention and played the 18th impressively whereas Berger did not bogeying the hole in regulation and the playoff. Rory WD prior to the 3rd round with a tweak in his back, Sepp was right in the mix on Sunday but really disappointed on the back 9 with a string of bogies. Kurt midway back. Eye Catchers - Min Woo Lee continues to impress on courses you wouldn’t think he we would excel on. Morikawa looks back to his best.
A183: 46083 | B183: PGA Tour | C183: Cognizant Classic | D183: The Champion Course, PGA National Resort | E183: Course The Champion Course, PGA National Resort, Palm Beach Gardens, Florida Length 7,223 yards Par 71 Three par-fives; 11 par-fours; four par-threes Course type Parkland Course overview The Champions, a course created by George Fazio and redesigned by Jack Nicklaus, used to be one of the toughest layouts on the PGA Tour. The Honda Classic, renamed the Cognizant Classic in 2024, has been at this venue since 2007, with 72-hole totals of just six under par or worse enough to top the leaderboard four times. Over recent years, though, the PGA Tour has made the layout easier, changing the tenth hole from a par four to a par five in 2024, overseeding the track with Ryegrass to soften the turf, shortening the rough and widening the fairways. Thicker rough has been a feature of PGA Tour venues this season, so anything double-figures under par may have a winning chance this time. What will it take to win the Cognizant Classic? Three breezy days should make this more of a grind than has been the case recently, so accuracy from tee to green should prove the key to success. | F183: S.H. Kim | G183: Pre | H183: First Round Leader E/W | I183: 70-1 | J183: 1/4 Top 5 | K183: 2.5 | L183: Bet365 | M183: N/A | N183: Loss | O183: 0 | P183: =SUM(O183-K183) -> -2.5 | Q183: Nico Echavarria | R183: 50-1 | S183: - Dry but windy throughout most of the week will make it a tougher course than it has been in recent years. - Relatively long but overseeded rye makes it gettable even out of the rough. Water everywhere here, features on 16 holes. - [x] Michael Thorbjornson has to win soon surely? T39 on debut last year, master T2G and if he can have a good week with the putter in a field like this he will have a great chance of shaking off the maiden tag. - [x] Nico Echavarria has had a slow start this season since getting married towards the end of last year. T8 at Pebble a few weeks back shows his game is creeping back to form, missed cut at the Genesis I can forgive given the difficult greens. He is a Florida resident and I’m sure he will appreciate being back on bermudagrass. T21 best finish in 2024, this two time PGA winner is undervalues in this market at 60-1. - [x] Adam Hadwin is now on the Korn Ferry following a really disappointing year last year. I think he’s better than that, and with the few opportunities he will get to play in PGA tour events, he needs to make them count. He’s here this week as an alt player and usually like the wind. Could go well at a big price. | T183: A crazy finish saw Echavarria snatch a win after Lowry completely bottles it, hitting it in the drink off the 16th tee and again on the par3 17th. I thought the course played better this year, wind made it interesting and the greens were firm meaning you were still at some disadvantage playing out of the overseeded rye rough. That is Echavarrias third PGA tour win, an underrated player in my view and seems to thrive when under pressure. Eye-catchers - Castillo looked good and ready to breakthrough soon.
A184: 46078 | B184: PGA Tour | C184: Cognizant Classic | D184: The Champion Course, PGA National Resort | E184: Course The Champion Course, PGA National Resort, Palm Beach Gardens, Florida Length 7,223 yards Par 71 Three par-fives; 11 par-fours; four par-threes Course type Parkland Course overview The Champions, a course created by George Fazio and redesigned by Jack Nicklaus, used to be one of the toughest layouts on the PGA Tour. The Honda Classic, renamed the Cognizant Classic in 2024, has been at this venue since 2007, with 72-hole totals of just six under par or worse enough to top the leaderboard four times. Over recent years, though, the PGA Tour has made the layout easier, changing the tenth hole from a par four to a par five in 2024, overseeding the track with Ryegrass to soften the turf, shortening the rough and widening the fairways. Thicker rough has been a feature of PGA Tour venues this season, so anything double-figures under par may have a winning chance this time. What will it take to win the Cognizant Classic? Three breezy days should make this more of a grind than has been the case recently, so accuracy from tee to green should prove the key to success. | F184: Aaron Rai | G184: Pre | H184: First Round Leader E/W | I184: 45-1 | J184: 1/4 Top 5 | K184: 2.5 | L184: Bet365 | M184: N/A | N184: Loss | O184: 0 | P184: =SUM(O184-K184) -> -2.5 | Q184: Nico Echavarria | R184: 50-1 | S184: - Dry but windy throughout most of the week will make it a tougher course than it has been in recent years. - Relatively long but overseeded rye makes it gettable even out of the rough. Water everywhere here, features on 16 holes. - [x] Michael Thorbjornson has to win soon surely? T39 on debut last year, master T2G and if he can have a good week with the putter in a field like this he will have a great chance of shaking off the maiden tag. - [x] Nico Echavarria has had a slow start this season since getting married towards the end of last year. T8 at Pebble a few weeks back shows his game is creeping back to form, missed cut at the Genesis I can forgive given the difficult greens. He is a Florida resident and I’m sure he will appreciate being back on bermudagrass. T21 best finish in 2024, this two time PGA winner is undervalues in this market at 60-1. - [x] Adam Hadwin is now on the Korn Ferry following a really disappointing year last year. I think he’s better than that, and with the few opportunities he will get to play in PGA tour events, he needs to make them count. He’s here this week as an alt player and usually like the wind. Could go well at a big price. | T184: A crazy finish saw Echavarria snatch a win after Lowry completely bottles it, hitting it in the drink off the 16th tee and again on the par3 17th. I thought the course played better this year, wind made it interesting and the greens were firm meaning you were still at some disadvantage playing out of the overseeded rye rough. That is Echavarrias third PGA tour win, an underrated player in my view and seems to thrive when under pressure. Eye-catchers - Castillo looked good and ready to breakthrough soon.
A185: 46078 | B185: DP World Tour | C185: Investec South African Open | D185: Stellenbosch GC | E185: Course Stellenbosch Golf Club, Stellenbosch, South Africa Length 7,213 yards Par 70 Two par-fives; 12 par-fours; four par-threes Course type Parkland Course overview Stellenbosch is hosting the South African Open for the first time since 1999 – when David Frost won with a five-under-par 72-hole total. Two 54-hole Sunshine Tour events have taken place at Stellenbosch since – the 2010 and 2019 Vodacom Origins event. The course has been upgraded and lengthened since. The fairways are kikuyu grass and the greens are bentgrass. Long par-fours and short par-threes are a feature of the course. What will it take to win the South African Open? The course was set up easier for the Vodacom Origins events, with 54-hole winning scores of 17 under and 15 under, but the layout has been toughened up since and grinding greens in regulation will probably be the key to success. | F185: Joakim Lagergren | G185: Pre | H185: First Round Leader E/W | I185: 70-1 | J185: 1/4 Top 5 | K185: 2.5 | L185: Bet365 | M185: N/A | N185: Loss | O185: 0 | P185: =SUM(O185-K185) -> -2.5 | Q185: Casey Jarvis | R185: 25-1 | S185: - Looking for decent approach play - SA players have won this the last 8 events - The event is played at a different course each year. - [x] Branden Grace has a decent record winning this in 2020 and T4 last year when in Durban (reduced to 54 holes). He’s also been playing good golf this year on LIV & the Dunhill championship back in December, not finishing outside of the top10. Dropping down in grade you could say for this week and this course should suit his game. - [ ] Jayden Schaper - [ ] Jacob Olesen - [x] Kieren Vincent - [x] Oliver Bekker | T185: Casey Jarvis does it again, I was slightly disappointed I overlooked him for this considering how good a player he is and the nature of players winning back to back this year especially in South Africa. Branden Grace was the only one out of mine that made the cut and was very underwhelming at the weekend. Stellenbosch is a decent course, down by the Cape Town region of SA. This means not as much altitude compared to when they play in other areas. Played firm with SA players featuring heavily again, they do seem much more accustom to the grasses.
A186: 46078 | B186: DP World Tour | C186: Investec South African Open | D186: Stellenbosch GC | E186: Course Stellenbosch Golf Club, Stellenbosch, South Africa Length 7,213 yards Par 70 Two par-fives; 12 par-fours; four par-threes Course type Parkland Course overview Stellenbosch is hosting the South African Open for the first time since 1999 – when David Frost won with a five-under-par 72-hole total. Two 54-hole Sunshine Tour events have taken place at Stellenbosch since – the 2010 and 2019 Vodacom Origins event. The course has been upgraded and lengthened since. The fairways are kikuyu grass and the greens are bentgrass. Long par-fours and short par-threes are a feature of the course. What will it take to win the South African Open? The course was set up easier for the Vodacom Origins events, with 54-hole winning scores of 17 under and 15 under, but the layout has been toughened up since and grinding greens in regulation will probably be the key to success. | F186: Thriston Lawrence | G186: Pre | H186: First Round Leader E/W | I186: 45-1 | J186: 1/4 Top 5 | K186: 2.5 | L186: Coral | M186: N/A | N186: Loss | O186: 0 | P186: =SUM(O186-K186) -> -2.5 | Q186: Casey Jarvis | R186: 25-1 | S186: - Looking for decent approach play - SA players have won this the last 8 events - The event is played at a different course each year. - [x] Branden Grace has a decent record winning this in 2020 and T4 last year when in Durban (reduced to 54 holes). He’s also been playing good golf this year on LIV & the Dunhill championship back in December, not finishing outside of the top10. Dropping down in grade you could say for this week and this course should suit his game. - [ ] Jayden Schaper - [ ] Jacob Olesen - [x] Kieren Vincent - [x] Oliver Bekker | T186: Casey Jarvis does it again, I was slightly disappointed I overlooked him for this considering how good a player he is and the nature of players winning back to back this year especially in South Africa. Branden Grace was the only one out of mine that made the cut and was very underwhelming at the weekend. Stellenbosch is a decent course, down by the Cape Town region of SA. This means not as much altitude compared to when they play in other areas. Played firm with SA players featuring heavily again, they do seem much more accustom to the grasses.
A187: 46078 | B187: N/A | C187: Cognizant Classic / Investec South African Open | D187: N/A | F187: Branden Grace / Michael Thorbjornson | G187: Pre | H187: E/W Double | I187: 441-1 | J187: 1/4 Top 5 | K187: 2 | L187: Bet365 | M187: N/A | N187: Loss | O187: 0 | P187: =SUM(O187-K187) -> -2 | Q187: N/A | R187: N/A | S187: N/A | T187: N/A
A188: 46076 | B188: PGA Tour | C188: Cognizant Classic | D188: The Champion Course, PGA National Resort | E188: Course The Champion Course, PGA National Resort, Palm Beach Gardens, Florida Length 7,223 yards Par 71 Three par-fives; 11 par-fours; four par-threes Course type Parkland Course overview The Champions, a course created by George Fazio and redesigned by Jack Nicklaus, used to be one of the toughest layouts on the PGA Tour. The Honda Classic, renamed the Cognizant Classic in 2024, has been at this venue since 2007, with 72-hole totals of just six under par or worse enough to top the leaderboard four times. Over recent years, though, the PGA Tour has made the layout easier, changing the tenth hole from a par four to a par five in 2024, overseeding the track with Ryegrass to soften the turf, shortening the rough and widening the fairways. Thicker rough has been a feature of PGA Tour venues this season, so anything double-figures under par may have a winning chance this time. What will it take to win the Cognizant Classic? Three breezy days should make this more of a grind than has been the case recently, so accuracy from tee to green should prove the key to success. | F188: Michael Thorbjornson | G188: Pre | H188: E/W | I188: 22-1 | J188: 1/5 Top 8 | K188: 15 | L188: SkyBet | M188: CUT | N188: Loss | O188: 0 | P188: =SUM(O188-K188) -> -15 | Q188: Nico Echavarria | R188: 50-1 | S188: - Dry but windy throughout most of the week will make it a tougher course than it has been in recent years. - Relatively long but overseeded rye makes it gettable even out of the rough. Water everywhere here, features on 16 holes. - [x] Michael Thorbjornson has to win soon surely? T39 on debut last year, master T2G and if he can have a good week with the putter in a field like this he will have a great chance of shaking off the maiden tag. - [x] Nico Echavarria has had a slow start this season since getting married towards the end of last year. T8 at Pebble a few weeks back shows his game is creeping back to form, missed cut at the Genesis I can forgive given the difficult greens. He is a Florida resident and I’m sure he will appreciate being back on bermudagrass. T21 best finish in 2024, this two time PGA winner is undervalues in this market at 60-1. - [x] Adam Hadwin is now on the Korn Ferry following a really disappointing year last year. I think he’s better than that, and with the few opportunities he will get to play in PGA tour events, he needs to make them count. He’s here this week as an alt player and usually like the wind. Could go well at a big price. | T188: A crazy finish saw Echavarria snatch a win after Lowry completely bottles it, hitting it in the drink off the 16th tee and again on the par3 17th. I thought the course played better this year, wind made it interesting and the greens were firm meaning you were still at some disadvantage playing out of the overseeded rye rough. That is Echavarrias third PGA tour win, an underrated player in my view and seems to thrive when under pressure. Eye-catchers - Castillo looked good and ready to breakthrough soon.
A189: 46076 | B189: PGA Tour | C189: Cognizant Classic | D189: The Champion Course, PGA National Resort | E189: Course The Champion Course, PGA National Resort, Palm Beach Gardens, Florida Length 7,223 yards Par 71 Three par-fives; 11 par-fours; four par-threes Course type Parkland Course overview The Champions, a course created by George Fazio and redesigned by Jack Nicklaus, used to be one of the toughest layouts on the PGA Tour. The Honda Classic, renamed the Cognizant Classic in 2024, has been at this venue since 2007, with 72-hole totals of just six under par or worse enough to top the leaderboard four times. Over recent years, though, the PGA Tour has made the layout easier, changing the tenth hole from a par four to a par five in 2024, overseeding the track with Ryegrass to soften the turf, shortening the rough and widening the fairways. Thicker rough has been a feature of PGA Tour venues this season, so anything double-figures under par may have a winning chance this time. What will it take to win the Cognizant Classic? Three breezy days should make this more of a grind than has been the case recently, so accuracy from tee to green should prove the key to success. | F189: Adam Hadwin | G189: Pre | H189: E/W | I189: 125-1 | J189: 1/5 Top 8 | L189: Bet365 | M189: CUT | N189: Loss | O189: 0 | P189: =SUM(O189-K189) -> 0 | Q189: Nico Echavarria | R189: 50-1 | S189: - Dry but windy throughout most of the week will make it a tougher course than it has been in recent years. - Relatively long but overseeded rye makes it gettable even out of the rough. Water everywhere here, features on 16 holes. - [x] Michael Thorbjornson has to win soon surely? T39 on debut last year, master T2G and if he can have a good week with the putter in a field like this he will have a great chance of shaking off the maiden tag. - [x] Nico Echavarria has had a slow start this season since getting married towards the end of last year. T8 at Pebble a few weeks back shows his game is creeping back to form, missed cut at the Genesis I can forgive given the difficult greens. He is a Florida resident and I’m sure he will appreciate being back on bermudagrass. T21 best finish in 2024, this two time PGA winner is undervalues in this market at 60-1. - [x] Adam Hadwin is now on the Korn Ferry following a really disappointing year last year. I think he’s better than that, and with the few opportunities he will get to play in PGA tour events, he needs to make them count. He’s here this week as an alt player and usually like the wind. Could go well at a big price. | T189: A crazy finish saw Echavarria snatch a win after Lowry completely bottles it, hitting it in the drink off the 16th tee and again on the par3 17th. I thought the course played better this year, wind made it interesting and the greens were firm meaning you were still at some disadvantage playing out of the overseeded rye rough. That is Echavarrias third PGA tour win, an underrated player in my view and seems to thrive when under pressure. Eye-catchers - Castillo looked good and ready to breakthrough soon.
A190: 46076 | B190: PGA Tour | C190: Cognizant Classic | D190: The Champion Course, PGA National Resort | E190: Course The Champion Course, PGA National Resort, Palm Beach Gardens, Florida Length 7,223 yards Par 71 Three par-fives; 11 par-fours; four par-threes Course type Parkland Course overview The Champions, a course created by George Fazio and redesigned by Jack Nicklaus, used to be one of the toughest layouts on the PGA Tour. The Honda Classic, renamed the Cognizant Classic in 2024, has been at this venue since 2007, with 72-hole totals of just six under par or worse enough to top the leaderboard four times. Over recent years, though, the PGA Tour has made the layout easier, changing the tenth hole from a par four to a par five in 2024, overseeding the track with Ryegrass to soften the turf, shortening the rough and widening the fairways. Thicker rough has been a feature of PGA Tour venues this season, so anything double-figures under par may have a winning chance this time. What will it take to win the Cognizant Classic? Three breezy days should make this more of a grind than has been the case recently, so accuracy from tee to green should prove the key to success. | F190: Nico Echavarria | G190: Pre | H190: E/W | I190: 60-1 | J190: 1/5 Top 10 | K190: 7.5 | L190: Coral | M190: 1 | N190: Win | O190: 277.5 | P190: =SUM(O190-K190) -> 270 | Q190: Nico Echavarria | R190: 50-1 | S190: - Dry but windy throughout most of the week will make it a tougher course than it has been in recent years. - Relatively long but overseeded rye makes it gettable even out of the rough. Water everywhere here, features on 16 holes. - [x] Michael Thorbjornson has to win soon surely? T39 on debut last year, master T2G and if he can have a good week with the putter in a field like this he will have a great chance of shaking off the maiden tag. - [x] Nico Echavarria has had a slow start this season since getting married towards the end of last year. T8 at Pebble a few weeks back shows his game is creeping back to form, missed cut at the Genesis I can forgive given the difficult greens. He is a Florida resident and I’m sure he will appreciate being back on bermudagrass. T21 best finish in 2024, this two time PGA winner is undervalues in this market at 60-1. - [x] Adam Hadwin is now on the Korn Ferry following a really disappointing year last year. I think he’s better than that, and with the few opportunities he will get to play in PGA tour events, he needs to make them count. He’s here this week as an alt player and usually like the wind. Could go well at a big price. | T190: A crazy finish saw Echavarria snatch a win after Lowry completely bottles it, hitting it in the drink off the 16th tee and again on the par3 17th. I thought the course played better this year, wind made it interesting and the greens were firm meaning you were still at some disadvantage playing out of the overseeded rye rough. That is Echavarrias third PGA tour win, an underrated player in my view and seems to thrive when under pressure. Eye-catchers - Castillo looked good and ready to breakthrough soon.
A191: 46076 | B191: DP World Tour | C191: Investec South African Open | D191: Stellenbosch GC | E191: Course Stellenbosch Golf Club, Stellenbosch, South Africa Length 7,213 yards Par 70 Two par-fives; 12 par-fours; four par-threes Course type Parkland Course overview Stellenbosch is hosting the South African Open for the first time since 1999 – when David Frost won with a five-under-par 72-hole total. Two 54-hole Sunshine Tour events have taken place at Stellenbosch since – the 2010 and 2019 Vodacom Origins event. The course has been upgraded and lengthened since. The fairways are kikuyu grass and the greens are bentgrass. Long par-fours and short par-threes are a feature of the course. What will it take to win the South African Open? The course was set up easier for the Vodacom Origins events, with 54-hole winning scores of 17 under and 15 under, but the layout has been toughened up since and grinding greens in regulation will probably be the key to success. | F191: Oliver Bekker | G191: Pre | H191: E/W | I191: 90-1 | J191: 1/5 Top 10 | K191: 5 | L191: SkyBet | M191: CUT | N191: Loss | O191: 0 | P191: =SUM(O191-K191) -> -5 | Q191: Casey Jarvis | R191: 25-1 | S191: - Looking for decent approach play - SA players have won this the last 8 events - The event is played at a different course each year. - [x] Branden Grace has a decent record winning this in 2020 and T4 last year when in Durban (reduced to 54 holes). He’s also been playing good golf this year on LIV & the Dunhill championship back in December, not finishing outside of the top10. Dropping down in grade you could say for this week and this course should suit his game. - [ ] Jayden Schaper - [ ] Jacob Olesen - [x] Kieren Vincent - [x] Oliver Bekker | T191: Casey Jarvis does it again, I was slightly disappointed I overlooked him for this considering how good a player he is and the nature of players winning back to back this year especially in South Africa. Branden Grace was the only one out of mine that made the cut and was very underwhelming at the weekend. Stellenbosch is a decent course, down by the Cape Town region of SA. This means not as much altitude compared to when they play in other areas. Played firm with SA players featuring heavily again, they do seem much more accustom to the grasses.
A192: 46076 | B192: DP World Tour | C192: Investec South African Open | D192: Stellenbosch GC | E192: Course Stellenbosch Golf Club, Stellenbosch, South Africa Length 7,213 yards Par 70 Two par-fives; 12 par-fours; four par-threes Course type Parkland Course overview Stellenbosch is hosting the South African Open for the first time since 1999 – when David Frost won with a five-under-par 72-hole total. Two 54-hole Sunshine Tour events have taken place at Stellenbosch since – the 2010 and 2019 Vodacom Origins event. The course has been upgraded and lengthened since. The fairways are kikuyu grass and the greens are bentgrass. Long par-fours and short par-threes are a feature of the course. What will it take to win the South African Open? The course was set up easier for the Vodacom Origins events, with 54-hole winning scores of 17 under and 15 under, but the layout has been toughened up since and grinding greens in regulation will probably be the key to success. | F192: Branden Grace | G192: Pre | H192: E/W | I192: 22-1 | J192: 1/5 Top 8 | K192: 15 | L192: SkyBet | M192: T20 | N192: Loss | O192: 0 | P192: =SUM(O192-K192) -> -15 | Q192: Casey Jarvis | R192: 25-1 | S192: - Looking for decent approach play - SA players have won this the last 8 events - The event is played at a different course each year. - [x] Branden Grace has a decent record winning this in 2020 and T4 last year when in Durban (reduced to 54 holes). He’s also been playing good golf this year on LIV & the Dunhill championship back in December, not finishing outside of the top10. Dropping down in grade you could say for this week and this course should suit his game. - [ ] Jayden Schaper - [ ] Jacob Olesen - [x] Kieren Vincent - [x] Oliver Bekker | T192: Casey Jarvis does it again, I was slightly disappointed I overlooked him for this considering how good a player he is and the nature of players winning back to back this year especially in South Africa. Branden Grace was the only one out of mine that made the cut and was very underwhelming at the weekend. Stellenbosch is a decent course, down by the Cape Town region of SA. This means not as much altitude compared to when they play in other areas. Played firm with SA players featuring heavily again, they do seem much more accustom to the grasses.
A193: 46076 | B193: DP World Tour | C193: Investec South African Open | D193: Stellenbosch GC | E193: Course Stellenbosch Golf Club, Stellenbosch, South Africa Length 7,213 yards Par 70 Two par-fives; 12 par-fours; four par-threes Course type Parkland Course overview Stellenbosch is hosting the South African Open for the first time since 1999 – when David Frost won with a five-under-par 72-hole total. Two 54-hole Sunshine Tour events have taken place at Stellenbosch since – the 2010 and 2019 Vodacom Origins event. The course has been upgraded and lengthened since. The fairways are kikuyu grass and the greens are bentgrass. Long par-fours and short par-threes are a feature of the course. What will it take to win the South African Open? The course was set up easier for the Vodacom Origins events, with 54-hole winning scores of 17 under and 15 under, but the layout has been toughened up since and grinding greens in regulation will probably be the key to success. | F193: Kieran Vincent | G193: Pre | H193: E/W | I193: 80-1 | J193: 1/5 Top 8 | K193: 5 | L193: Bet365 | M193: CUT | N193: Loss | O193: 0 | P193: =SUM(O193-K193) -> -5 | Q193: Casey Jarvis | R193: 25-1 | S193: - Looking for decent approach play - SA players have won this the last 8 events - The event is played at a different course each year. - [x] Branden Grace has a decent record winning this in 2020 and T4 last year when in Durban (reduced to 54 holes). He’s also been playing good golf this year on LIV & the Dunhill championship back in December, not finishing outside of the top10. Dropping down in grade you could say for this week and this course should suit his game. - [ ] Jayden Schaper - [ ] Jacob Olesen - [x] Kieren Vincent - [x] Oliver Bekker | T193: Casey Jarvis does it again, I was slightly disappointed I overlooked him for this considering how good a player he is and the nature of players winning back to back this year especially in South Africa. Branden Grace was the only one out of mine that made the cut and was very underwhelming at the weekend. Stellenbosch is a decent course, down by the Cape Town region of SA. This means not as much altitude compared to when they play in other areas. Played firm with SA players featuring heavily again, they do seem much more accustom to the grasses.
A194: 46076 | B194: DP World Tour | C194: Magical Kenya Open | D194: Karen Country Club | E194: Course Karen Country Club, Nairobi, Kenya Length 7,056 yards Par 70 Course make-up Two par-fives; 12 par-fours; four par-threes Course type Parkland Course overview Karen Country Club hosts this tournament for the first time since 2021 and the Kenya Open has twice been contested here since it graduated to the DP World Tour from the Challenge Tour in 2019. The last three have been played at the Muthaiga Golf Club in Karura. The course is just outside the Kenyan capital and is a short track. Nairobi's altitude of just under 1,800m above sea level means the ball will fly further than normal. The fairways, which are Kikuyu grass, are pretty flat although many a tree-lined so accuracy could play a part, while the greens are bentgrass. What will it take to win? The altitude should negate the advantage of distance off the tee, so if fairways can be regularly found, this could turn into a putting contest. | F194: Darius Van Driel | G194: Pre | H194: First Round Leader E/W | I194: 70-1 | J194: 1/4 Top 5 | K194: 2.5 | L194: Bet365 | M194: N/A | N194: Loss | O194: 0 | P194: =SUM(O194-K194) -> -2.5 | Q194: Casey Jarvis | R194: 35-1 | S194: - [x] Josh Berry - [x] Thriston Lawerence - [x] Darius Van Driel | T194: Casey Jarvis has got over the line after coming close in the past, especially Mauritius from my memory. I thought of him as a classy player but lacked the composure to get across the line. He gave himself a nice cushion for Sunday and was put under some pressure by Davis Bryant but had it his own way. Will be worth keeping an eye on him now he’s got that win. Thriston Lawerence was the only player from my bets to make the cut but a really disappointing 71 on Saturday put his chances to rest. Eye-catchers - Hennie Du Plesis looks really good, a few small mistakes cost him on Sunday but game looks bang in form. JS Olesen continues to impress, another top5.
A195: 46071 | B195: DP World Tour | C195: Magical Kenya Open | D195: Karen Country Club | E195: Course Karen Country Club, Nairobi, Kenya Length 7,056 yards Par 70 Course make-up Two par-fives; 12 par-fours; four par-threes Course type Parkland Course overview Karen Country Club hosts this tournament for the first time since 2021 and the Kenya Open has twice been contested here since it graduated to the DP World Tour from the Challenge Tour in 2019. The last three have been played at the Muthaiga Golf Club in Karura. The course is just outside the Kenyan capital and is a short track. Nairobi's altitude of just under 1,800m above sea level means the ball will fly further than normal. The fairways, which are Kikuyu grass, are pretty flat although many a tree-lined so accuracy could play a part, while the greens are bentgrass. What will it take to win? The altitude should negate the advantage of distance off the tee, so if fairways can be regularly found, this could turn into a putting contest. | F195: Gregorio De Leo | G195: Pre | H195: First Round Leader E/W | I195: 80-1 | J195: 1/4 Top 5 | K195: 2.5 | L195: Coral | M195: N/A | N195: Loss | O195: 0 | P195: =SUM(O195-K195) -> -2.5 | Q195: Casey Jarvis | R195: 35-1 | S195: - [x] Josh Berry - [x] Thriston Lawerence - [x] Darius Van Driel | T195: Casey Jarvis has got over the line after coming close in the past, especially Mauritius from my memory. I thought of him as a classy player but lacked the composure to get across the line. He gave himself a nice cushion for Sunday and was put under some pressure by Davis Bryant but had it his own way. Will be worth keeping an eye on him now he’s got that win. Thriston Lawerence was the only player from my bets to make the cut but a really disappointing 71 on Saturday put his chances to rest. Eye-catchers - Hennie Du Plesis looks really good, a few small mistakes cost him on Sunday but game looks bang in form. JS Olesen continues to impress, another top5.
A196: 46071 | B196: PGA Tour | C196: Genesis Invitational | D196: Riviera Country Club | E196: Course Riviera Country Club, Pacific Palisades, California, USA Lengths 7,383 yards Par 71 Course type Parkland Course overview Riviera Country Club has been home for the tournament that started out in 1926 as the Los Angeles Open and in all its subsequent guises since 1973, except for in 1983, 1998 and last year, when fire damage meant the tournament was moved to Torrey Pines South. Players will be presented with a course that needs to be managed and has unusual features, such as a par-three sixth that has a bunker in the middle of the green. And while the par-four tenth is driveable, it's a huge task to find the small green and danger lies around the edge. Finding the kikuyu fairways is key as the rough presents all sorts of problems and the greens are poa annua. What will it take to win? Riviera is a great test of course management and the savviest players often go well. Accurate iron play has been a key to success while scrambling ability and solid putting can often tip the balance. Course experience is a huge benefit too. | F196: Sam Burns | G196: Pre | H196: First Round Leader E/W | I196: 40-1 | J196: 1/4 Top 5 | K196: 5 | L196: PaddyPower | M196: N/A | N196: Loss | O196: 0 | P196: =SUM(O196-K196) -> -5 | Q196: Jacob Bridgeman | R196: 80-1 | S196: - Different type of grass at Riv, it’s similar to Torrey Fairways: Kikuyugrass; Rough: Kikuyugrass 2″; 7,500 sq.ft average featuring Poa Annua; Tournament Stimp: 12.5ft. - Looking for good putters on this surface, T2G, GIR important here as is a decent APP - [ ] Tommy - [ ] Fitz - [x] Hideki Matsuyama - [x] Ryan Fox - [x] Ludvig Aberg | T196: Jacob Bridgemen gave himself a nice cushion of 6 from Rory after a brilliant Saturday round. He headed the field in putting & approach negating his driver length which is usually a trait that’s needed here. Really impressive after a disappointing finish at Pebble beach last week. Rory looked really good but couldn’t putt throughout the weekend. Ryan Fox the best of my bets finishing a good T7 for 125-1. Interested to see Xander come back to form, like Rory struggled with the putter at the weekend but I expect big things from him in near future. Eye-catchers - Kurt Kitayama looks back to his best, pure class ball striker.
A197: 18/02/2026 | B197: PGA Tour | C197: Genesis Invitational | D197: Riviera Country Club | E197: Course Riviera Country Club, Pacific Palisades, California, USA Lengths 7,383 yards Par 71 Course type Parkland Course overview Riviera Country Club has been home for the tournament that started out in 1926 as the Los Angeles Open and in all its subsequent guises since 1973, except for in 1983, 1998 and last year, when fire damage meant the tournament was moved to Torrey Pines South. Players will be presented with a course that needs to be managed and has unusual features, such as a par-three sixth that has a bunker in the middle of the green. And while the par-four tenth is driveable, it's a huge task to find the small green and danger lies around the edge. Finding the kikuyu fairways is key as the rough presents all sorts of problems and the greens are poa annua. What will it take to win? Riviera is a great test of course management and the savviest players often go well. Accurate iron play has been a key to success while scrambling ability and solid putting can often tip the balance. Course experience is a huge benefit too. | F197: Ludvig Aberg | G197: Pre | H197: E/W | I197: 40-1 | J197: 1/5 Top 8 | K197: 10 | L197: Bet365 | M197: T20 | N197: Loss | O197: 0 | P197: =SUM(O197-K197) -> -10 | Q197: Jacob Bridgeman | R197: 80-1 | S197: - Different type of grass at Riv, it’s similar to Torrey Fairways: Kikuyugrass; Rough: Kikuyugrass 2″; 7,500 sq.ft average featuring Poa Annua; Tournament Stimp: 12.5ft. - Looking for good putters on this surface, T2G, GIR important here as is a decent APP - [ ] Tommy - [ ] Fitz - [x] Hideki Matsuyama - [x] Ryan Fox - [x] Ludvig Aberg | T197: Jacob Bridgemen gave himself a nice cushion of 6 from Rory after a brilliant Saturday round. He headed the field in putting & approach negating his driver length which is usually a trait that’s needed here. Really impressive after a disappointing finish at Pebble beach last week. Rory looked really good but couldn’t putt throughout the weekend. Ryan Fox the best of my bets finishing a good T7 for 125-1. Interested to see Xander come back to form, like Rory struggled with the putter at the weekend but I expect big things from him in near future. Eye-catchers - Kurt Kitayama looks back to his best, pure class ball striker.
A198: 16/02/2026 | B198: N/A | C198: Magical Kenya Open/Genesis Invitational | D198: N/A | E198: N/A | F198: Thriston Lawrence/Hideki Matsuyama | G198: Pre | H198: E/W Double | I198: 500-1 | J198: 1/4 Top 5 | K198: 1.5 | L198: SkyBet | M198: N/A | N198: Loss | O198: 0 | P198: =SUM(O198-K198) -> -1.5 | Q198: N/A | R198: N/A | S198: N/A | T198: N/A
A199: 16/02/2026 | B199: PGA Tour | C199: Genesis Invitational | D199: Riviera Country Club | E199: Course Riviera Country Club, Pacific Palisades, California, USA Lengths 7,383 yards Par 71 Course type Parkland Course overview Riviera Country Club has been home for the tournament that started out in 1926 as the Los Angeles Open and in all its subsequent guises since 1973, except for in 1983, 1998 and last year, when fire damage meant the tournament was moved to Torrey Pines South. Players will be presented with a course that needs to be managed and has unusual features, such as a par-three sixth that has a bunker in the middle of the green. And while the par-four tenth is driveable, it's a huge task to find the small green and danger lies around the edge. Finding the kikuyu fairways is key as the rough presents all sorts of problems and the greens are poa annua. What will it take to win? Riviera is a great test of course management and the savviest players often go well. Accurate iron play has been a key to success while scrambling ability and solid putting can often tip the balance. Course experience is a huge benefit too. | F199: Ryan Fox | G199: Pre | H199: E/W | I199: 125-1 | J199: 1/5 Top 10 | K199: 3.75 | L199: SkyBet | M199: T7 | N199: Place | O199: 36.4 | P199: =SUM(O199-K199) -> 32.65 | Q199: Jacob Bridgeman | R199: 80-1 | S199: - Different type of grass at Riv, it’s similar to Torrey Fairways: Kikuyugrass; Rough: Kikuyugrass 2″; 7,500 sq.ft average featuring Poa Annua; Tournament Stimp: 12.5ft. - Looking for good putters on this surface, T2G, GIR important here as is a decent APP - [ ] Tommy - [ ] Fitz - [x] Hideki Matsuyama - [x] Ryan Fox - [x] Ludvig Aberg | T199: Jacob Bridgemen gave himself a nice cushion of 6 from Rory after a brilliant Saturday round. He headed the field in putting & approach negating his driver length which is usually a trait that’s needed here. Really impressive after a disappointing finish at Pebble beach last week. Rory looked really good but couldn’t putt throughout the weekend. Ryan Fox the best of my bets finishing a good T7 for 125-1. Interested to see Xander come back to form, like Rory struggled with the putter at the weekend but I expect big things from him in near future. Eye-catchers - Kurt Kitayama looks back to his best, pure class ball striker.
A200: 16/02/2026 | B200: PGA Tour | C200: Genesis Invitational | D200: Riviera Country Club | E200: Course Riviera Country Club, Pacific Palisades, California, USA Lengths 7,383 yards Par 71 Course type Parkland Course overview Riviera Country Club has been home for the tournament that started out in 1926 as the Los Angeles Open and in all its subsequent guises since 1973, except for in 1983, 1998 and last year, when fire damage meant the tournament was moved to Torrey Pines South. Players will be presented with a course that needs to be managed and has unusual features, such as a par-three sixth that has a bunker in the middle of the green. And while the par-four tenth is driveable, it's a huge task to find the small green and danger lies around the edge. Finding the kikuyu fairways is key as the rough presents all sorts of problems and the greens are poa annua. What will it take to win? Riviera is a great test of course management and the savviest players often go well. Accurate iron play has been a key to success while scrambling ability and solid putting can often tip the balance. Course experience is a huge benefit too. | F200: Hideki Matsuyama | G200: Pre | H200: E/W | I200: 25-1 | J200: 1/4 Top 5 | K200: 15 | L200: SkyBet | M200: T28 | N200: Loss | O200: 0 | P200: =SUM(O200-K200) -> -15 | Q200: Jacob Bridgeman | R200: 80-1 | S200: - Different type of grass at Riv, it’s similar to Torrey Fairways: Kikuyugrass; Rough: Kikuyugrass 2″; 7,500 sq.ft average featuring Poa Annua; Tournament Stimp: 12.5ft. - Looking for good putters on this surface, T2G, GIR important here as is a decent APP - [ ] Tommy - [ ] Fitz - [x] Hideki Matsuyama - [x] Ryan Fox - [x] Ludvig Aberg | T200: Jacob Bridgemen gave himself a nice cushion of 6 from Rory after a brilliant Saturday round. He headed the field in putting & approach negating his driver length which is usually a trait that’s needed here. Really impressive after a disappointing finish at Pebble beach last week. Rory looked really good but couldn’t putt throughout the weekend. Ryan Fox the best of my bets finishing a good T7 for 125-1. Interested to see Xander come back to form, like Rory struggled with the putter at the weekend but I expect big things from him in near future. Eye-catchers - Kurt Kitayama looks back to his best, pure class ball striker.
A201: 46069 | B201: DP World Tour | C201: Magical Kenya Open | D201: Karen Country Club | E201: Course Karen Country Club, Nairobi, Kenya Length 7,056 yards Par 70 Course make-up Two par-fives; 12 par-fours; four par-threes Course type Parkland Course overview Karen Country Club hosts this tournament for the first time since 2021 and the Kenya Open has twice been contested here since it graduated to the DP World Tour from the Challenge Tour in 2019. The last three have been played at the Muthaiga Golf Club in Karura. The course is just outside the Kenyan capital and is a short track. Nairobi's altitude of just under 1,800m above sea level means the ball will fly further than normal. The fairways, which are Kikuyu grass, are pretty flat although many a tree-lined so accuracy could play a part, while the greens are bentgrass. What will it take to win? The altitude should negate the advantage of distance off the tee, so if fairways can be regularly found, this could turn into a putting contest. | F201: Darius Van Driel | G201: Pre | H201: E/W | I201: 66-1 | J201: 1/5 Top 8 | K201: 5 | L201: Bet365 | M201: CUT | N201: Loss | O201: 0 | P201: =SUM(O201-K201) -> -5 | Q201: Casey Jarvis | R201: 35-1 | S201: - [x] Josh Berry - [x] Thriston Lawerence - [x] Darius Van Driel | T201: Casey Jarvis has got over the line after coming close in the past, especially Mauritius from my memory. I thought of him as a classy player but lacked the composure to get across the line. He gave himself a nice cushion for Sunday and was put under some pressure by Davis Bryant but had it his own way. Will be worth keeping an eye on him now he’s got that win. Thriston Lawerence was the only player from my bets to make the cut but a really disappointing 71 on Saturday put his chances to rest. Eye-catchers - Hennie Du Plesis looks really good, a few small mistakes cost him on Sunday but game looks bang in form. JS Olesen continues to impress, another top5.
A202: 46069 | B202: DP World Tour | C202: Magical Kenya Open | D202: Karen Country Club | E202: Course Karen Country Club, Nairobi, Kenya Length 7,056 yards Par 70 Course make-up Two par-fives; 12 par-fours; four par-threes Course type Parkland Course overview Karen Country Club hosts this tournament for the first time since 2021 and the Kenya Open has twice been contested here since it graduated to the DP World Tour from the Challenge Tour in 2019. The last three have been played at the Muthaiga Golf Club in Karura. The course is just outside the Kenyan capital and is a short track. Nairobi's altitude of just under 1,800m above sea level means the ball will fly further than normal. The fairways, which are Kikuyu grass, are pretty flat although many a tree-lined so accuracy could play a part, while the greens are bentgrass. What will it take to win? The altitude should negate the advantage of distance off the tee, so if fairways can be regularly found, this could turn into a putting contest. | F202: Thriston Lawrence | G202: Pre | H202: E/W | I202: 25-1 | J202: 1/5 Top 7 | K202: 15 | L202: Coral | M202: T29 | N202: Loss | O202: 0 | P202: =SUM(O202-K202) -> -15 | Q202: Casey Jarvis | R202: 35-1 | S202: - [x] Josh Berry - [x] Thriston Lawerence - [x] Darius Van Driel | T202: Casey Jarvis has got over the line after coming close in the past, especially Mauritius from my memory. I thought of him as a classy player but lacked the composure to get across the line. He gave himself a nice cushion for Sunday and was put under some pressure by Davis Bryant but had it his own way. Will be worth keeping an eye on him now he’s got that win. Thriston Lawerence was the only player from my bets to make the cut but a really disappointing 71 on Saturday put his chances to rest. Eye-catchers - Hennie Du Plesis looks really good, a few small mistakes cost him on Sunday but game looks bang in form. JS Olesen continues to impress, another top5.
...

Sheet 2026
A1: Golf Betting Record - 2025
A2: Tour/Majors | B2: DP World Tour | C2: LIV | D2: Majors | E2: Multiple | F2: Olympics | G2: PGA Tour | H2: Ryder Cup | I2: Grand Total
A3: Date (YM) | E3: Profit/Loss (Sum)
A4: 45078 | D4: 0 | I4: 0
A5: 45108 | D5: 0 | E5: 0 | I5: 0
A6: 45170 | B6: 0 | C6: 0 | H6: 0 | I6: 0
A7: 45200 | B7: 0 | E7: 0 | I7: 0
A8: 45352 | E8: 0 | G8: 0 | I8: 0
A9: 45383 | B9: 0 | C9: 0 | D9: 0 | E9: 0 | G9: 0 | I9: 0
A10: 45413 | B10: 0 | C10: 0 | D10: 0 | E10: 0 | G10: 0 | I10: 0
A11: 45444 | B11: 0 | C11: 0 | D11: 0 | E11: 0 | G11: 0 | I11: 0
A12: 45474 | B12: 0 | C12: 0 | D12: 0 | E12: 0 | F12: 0 | G12: 0 | I12: 0
A13: 45505 | B13: 0 | C13: 0 | E13: 0 | G13: 0 | I13: 0
A14: 45536 | B14: 0 | E14: 0 | G14: 0 | I14: 0
A15: 45566 | B15: 0 | E15: 0 | G15: 0 | I15: 0
A16: 45597 | B16: 0 | E16: 0 | G16: 0 | I16: 0
A17: 45689 | B17: 0 | D17: 0 | E17: 0 | G17: 0 | I17: 0
A18: 45717 | B18: 0 | D18: 0 | E18: 0 | G18: 0 | I18: 0
A19: 45748 | B19: 0 | C19: 0 | D19: 0 | E19: 0 | G19: 0 | I19: 0
A20: 45778 | B20: 0 | D20: 0 | E20: 0 | G20: 0 | I20: 0
A21: 45809 | B21: 0 | D21: 0 | E21: 0 | G21: 0 | I21: 0
A22: 45839 | B22: 0 | C22: 0 | D22: 0 | G22: 0 | I22: 0
A23: 45870 | B23: 0 | E23: 0 | G23: 0 | I23: 0
A24: 45901 | B24: 0 | E24: 0 | G24: 0 | H24: 0 | I24: 0
A25: 45931 | B25: 0 | G25: 0 | I25: 0
A26: 45962 | B26: 0 | G26: 0 | I26: 0
A27: 45992 | B27: 0 | I27: 0
A28: 46023 | E28: -20 | I28: -20
A29: Grand Total | B29: 0 | C29: 0 | D29: 0 | E29: -20 | F29: 0 | G29: 0 | H29: 0 | I29: -20
J31: Player - Places
M32: Outcome | N32: Loss | O32: Pending | P32: Place | Q32: Win | R32: Grand Total
J33: Place Terms | K33: Player | L33: Price | M33: Result
M34: T8 | N34: 0 | R34: 0
L35: 11-1 | N35: 0 | R35: 0
K36: Jason Day | N36: 0 | R36: 0
J37: 1/3 Top 2 | N37: 0 | R37: 0
M38: N/A | N38: 0 | R38: 0
L39: 45-1 | N39: 0 | R39: 0
K40: Ben Griffin | N40: 0 | R40: 0
M41: N/A | N41: 0 | R41: 0
L42: 45301 | N42: 0 | R42: 0
K43: Nick Taylor / Adam Hadwin | N43: 0 | R43: 0
M44: T16 | N44: 0 | R44: 0
L45: 18-1 | N45: 0 | R45: 0
K46: Rasmus Neergard-Petersen | N46: 0 | R46: 0
M47: T8 | N47: 0 | R47: 0
L48: 40-1 | N48: 0 | R48: 0
K49: Robert MacIntyre | N49: 0 | R49: 0
J50: 1/4 Top 3 | N50: 0 | R50: 0
M51: Pending | O51: 0 | R51: 0
L52: 18-1 | O52: 0 | R52: 0
K53: Viktor Hovland | O53: 0 | R53: 0
J54: 1/4 Top 4 | O54: 0 | R54: 0
M55: T54 | N55: 0 | R55: 0
L56: 30-1 | N56: 0 | R56: 0
K57: Adam Scott | N57: 0 | R57: 0
M58: T67 | N58: 0 | R58: 0
L59: 45-1 | N59: 0 | R59: 0
M60: N/A | N60: 0 | R60: 0
M61: T22 | N61: 0 | R61: 0
L62: 66-1 | N62: 0 | R62: 0
K63: Adrien Saddier | N63: 0 | R63: 0
M64: T2 | P64: 0 | R64: 0
L65: 20-1 | P65: 0 | R65: 0
M66: N/A | N66: 0 | R66: 0
M67: T61 | N67: 0 | R67: 0
L68: 35-1 | N68: 0 | R68: 0
M69: 1 | Q69: 0 | R69: 0
M70: N/A | N70: 0 | R70: 0
L71: 40-1 | N71: 0 | Q71: 0 | R71: 0
K72: Akshay Bhatia | N72: 0 | P72: 0 | Q72: 0 | R72: 0
M73: N/A | N73: 0 | R73: 0
L74: 389-1 | N74: 0 | R74: 0
K75: Akshay Bhatia/ Joe Dean | N75: 0 | R75: 0
M76: N/A | N76: 0 | R76: 0
L77: 130-1 | N77: 0 | R77: 0
K78: Alejandro Tosti | N78: 0 | R78: 0
M79: T55 | N79: 0 | R79: 0
L80: 50-1 | N80: 0 | R80: 0
M81: N/A | N81: 0 | R81: 0
L82: 66-1 | N82: 0 | R82: 0
M83: T20 | N83: 0 | R83: 0
L84: 75-1 | N84: 0 | R84: 0
K85: Alex Fitzpatrick | N85: 0 | R85: 0
M86: N/A | N86: 0 | R86: 0
L87: 60-1 | N87: 0 | R87: 0
K88: Alex Smalley | N88: 0 | R88: 0
M89: T36 | N89: 0 | R89: 0
L90: 70-1 | N90: 0 | R90: 0
K91: Andrea Pavan | N91: 0 | R91: 0
M92: T5 | P92: 0 | R92: 0
L93: 70-1 | P93: 0 | R93: 0
K94: Andrew Putman | P94: 0 | R94: 0
M95: T120 | N95: 0 | R95: 0
L96: 70-1 | N96: 0 | R96: 0
K97: Andy Sullivan | N97: 0 | R97: 0
M98: T8 | N98: 0 | R98: 0
L99: 22-1 | N99: 0 | R99: 0
M100: N/A | N100: 0 | R100: 0
L101: 60-1 | N101: 0 | R101: 0
...

Sheet 2025
A1: Golf Betting Record - 2025
A2: Tour/Majors | B2: DP World Tour | C2: LIV | D2: Majors | E2: Multiple | F2: Olympics | G2: PGA Tour | H2: Ryder Cup | I2: Grand Total
A3: Date (YM) | B3: Profit/Loss (Sum)
A4: 45078 | D4: 0 | I4: 0
A5: 45108 | D5: 0 | E5: 0 | I5: 0
A6: 45170 | B6: 0 | C6: 0 | H6: 0 | I6: 0
A7: 45200 | B7: 0 | E7: 0 | I7: 0
A8: 45352 | E8: 0 | G8: 0 | I8: 0
A9: 45383 | B9: 0 | C9: 0 | D9: 0 | E9: 0 | G9: 0 | I9: 0
A10: 45413 | B10: 0 | C10: 0 | D10: 0 | E10: 0 | G10: 0 | I10: 0
A11: 45444 | B11: 0 | C11: 0 | D11: 0 | E11: 0 | G11: 0 | I11: 0
A12: 45474 | B12: 0 | C12: 0 | D12: 0 | E12: 0 | F12: 0 | G12: 0 | I12: 0
A13: 45505 | B13: 0 | C13: 0 | E13: 0 | G13: 0 | I13: 0
A14: 45536 | B14: 0 | E14: 0 | G14: 0 | I14: 0
A15: 45566 | B15: 0 | E15: 0 | G15: 0 | I15: 0
A16: 45597 | B16: 0 | E16: 0 | G16: 0 | I16: 0
A17: 45689 | B17: -35 | D17: -5 | E17: -9.59 | G17: -60.75 | I17: -110.34
A18: 45717 | B18: 6.25 | D18: -10 | E18: -26.91 | G18: 54.38 | I18: 23.72
A19: 45748 | B19: -32.25 | C19: -10 | D19: 184.77 | E19: -5.5 | G19: -5.33 | I19: 131.69
A20: 45778 | B20: -73.5 | D20: -6.92 | E20: -2.5 | G20: 56.3 | I20: -26.62
A21: 45809 | B21: 39.25 | D21: 21 | E21: -5 | G21: 235.73 | I21: 290.98
A22: 45839 | B22: 32.5 | C22: -20 | D22: -72.5 | G22: 146.75 | I22: 86.75
A23: 45870 | B23: -53.25 | E23: -2.5 | G23: -117.5 | I23: -173.25
A24: 45901 | B24: 67.75 | E24: -2 | G24: 14.5 | H24: 42.5 | I24: 122.75
A25: 45931 | B25: -32 | G25: 0 | I25: -32
A26: 45962 | B26: -62.5 | G26: -16.93 | I26: -79.43
A27: 45992 | B27: 170.25 | I27: 170.25
A28: Grand Total | B28: 27.5 | C28: -30 | D28: 111.35 | E28: -54 | F28: 0 | G28: 307.15 | H28: 42.5 | I28: 404.5
J30: 2025 - Combined Outright & multiples
J31: Category | K31: Total
J32: DP World Tour | K32: 27.5
J33: Majors | K33: 111.35
J34: PGA Tour | K34: 307.15
J35: Multiple | K35: -54
J36: LIV | K36: -30
K37: 404.5
L39: Player - Places
O40: Outcome | P40: Loss | Q40: Pending | R40: Place | S40: Win | T40: Grand Total
L41: Place Terms | M41: Player | N41: Price | O41: Result | R41: Return (Sum)
O42: T8 | P42: 0 | T42: 0
N43: 11-1 | P43: 0 | T43: 0
M44: Jason Day | P44: 0 | T44: 0
L45: 1/3 Top 2 | P45: 0 | T45: 0
O46: N/A | P46: 0 | T46: 0
N47: 45-1 | P47: 0 | T47: 0
M48: Ben Griffin | P48: 0 | T48: 0
O49: N/A | P49: 0 | T49: 0
N50: 45301 | P50: 0 | T50: 0
M51: Nick Taylor / Adam Hadwin | P51: 0 | T51: 0
O52: T16 | P52: 0 | T52: 0
N53: 18-1 | P53: 0 | T53: 0
M54: Rasmus Neergard-Petersen | P54: 0 | T54: 0
O55: T8 | P55: 0 | T55: 0
N56: 40-1 | P56: 0 | T56: 0
M57: Robert MacIntyre | P57: 0 | T57: 0
L58: 1/4 Top 3 | P58: 0 | T58: 0
O59: Pending | Q59: 0 | T59: 0
N60: 18-1 | Q60: 0 | T60: 0
M61: Viktor Hovland | Q61: 0 | T61: 0
L62: 1/4 Top 4 | Q62: 0 | T62: 0
O63: T54 | P63: 0 | T63: 0
N64: 30-1 | P64: 0 | T64: 0
M65: Adam Scott | P65: 0 | T65: 0
O66: T67 | P66: 0 | T66: 0
N67: 45-1 | P67: 0 | T67: 0
O68: N/A | P68: 0 | T68: 0
O69: T22 | P69: 0 | T69: 0
N70: 66-1 | P70: 0 | T70: 0
M71: Adrien Saddier | P71: 0 | T71: 0
O72: T2 | R72: 0 | T72: 0
N73: 20-1 | R73: 0 | T73: 0
O74: N/A | P74: 0 | T74: 0
O75: T61 | P75: 0 | T75: 0
N76: 35-1 | P76: 0 | T76: 0
O77: 1 | S77: 0 | T77: 0
O78: N/A | P78: 0 | T78: 0
N79: 40-1 | P79: 0 | S79: 0 | T79: 0
M80: Akshay Bhatia | P80: 0 | R80: 0 | S80: 0 | T80: 0
O81: N/A | P81: 0 | T81: 0
N82: 389-1 | P82: 0 | T82: 0
M83: Akshay Bhatia/ Joe Dean | P83: 0 | T83: 0
O84: N/A | P84: 0 | T84: 0
N85: 130-1 | P85: 0 | T85: 0
M86: Alejandro Tosti | P86: 0 | T86: 0
O87: T55 | P87: 0 | T87: 0
N88: 50-1 | P88: 0 | T88: 0
O89: N/A | P89: 0 | T89: 0
N90: 66-1 | P90: 0 | T90: 0
O91: T20 | P91: 0 | T91: 0
N92: 75-1 | P92: 0 | T92: 0
M93: Alex Fitzpatrick | P93: 0 | T93: 0
O94: N/A | P94: 0 | T94: 0
N95: 60-1 | P95: 0 | T95: 0
M96: Alex Smalley | P96: 0 | T96: 0
O97: T36 | P97: 0 | T97: 0
N98: 70-1 | P98: 0 | T98: 0
M99: Andrea Pavan | P99: 0 | T99: 0
O100: T5 | R100: 0 | T100: 0
N101: 70-1 | R101: 0 | T101: 0
M102: Andrew Putman | R102: 0 | T102: 0
...

Sheet 2024
A1: Golf Betting Record - 2024
A2: Tour/Majors | B2: DP World Tour | C2: LIV | D2: Majors | E2: Multiple | F2: Olympics | G2: PGA Tour | H2: Ryder Cup | I2: Grand Total
A3: Date (YM) | B3: Profit/Loss (Sum)
A4: 45078 | D4: 0 | I4: 0
A5: 45108 | D5: 0 | E5: 0 | I5: 0
A6: 45170 | B6: 0 | C6: 0 | H6: 0 | I6: 0
A7: 45200 | B7: 0 | E7: 0 | I7: 0
A8: 45352 | E8: -5 | G8: 71.88 | I8: 66.88
A9: 45383 | B9: -32.5 | C9: -27.9 | D9: 87.5 | E9: 4.92 | G9: -33.75 | I9: -1.73
A10: 45413 | B10: -20 | C10: -2.5 | D10: -45.37 | E10: -25 | G10: 41.17 | I10: -51.7
A11: 45444 | B11: 175.5 | C11: -27.5 | D11: -12.5 | E11: -15 | G11: 102.5 | I11: 223
A12: 45474 | B12: -12.5 | C12: -40 | D12: 126.43 | E12: -5 | F12: -24.37 | G12: 87.5 | I12: 132.06
A13: 45505 | B13: 9.03 | C13: -10 | E13: -9.88 | G13: 145 | I13: 134.15
A14: 45536 | B14: -165.5 | E14: 6.09 | G14: -59.2 | I14: -218.61
A15: 45566 | B15: -54.5 | E15: 3.69 | G15: -8.58 | I15: -59.39
A16: 45597 | B16: 28 | E16: -3 | G16: -45 | I16: -20
A17: 45689 | G17: 0 | I17: 0
A18: Grand Total | B18: -72.47 | C18: -107.9 | D18: 156.06 | E18: -48.18 | F18: -24.37 | G18: 301.52 | H18: 0 | I18: 204.66
J20: 2024 - Combined Outright & multiples
J21: Category | K21: Total
J22: DP World Tour | K22: -72.47
J23: LIV | K23: -107.9
J24: Majors | K24: 156.06
J25: PGA Tour | K25: 301.52
J26: Multiple | K26: -48.18
J27: Olympics | K27: -24.37
K28: {=SUM(K22:K27)} -> 204.66
L30: Monthly ROI%
L31: Month | M31: Return On Investment
L32: {='ROI%'!$A$7} -> 45352 | M32: 4.4586667
L33: {='ROI%'!$A$8} -> 45383 | M33: -0.0085432099
L34: {='ROI%'!$A$9} -> 45413 | M34: -0.23770115
L35: 45444 | M35: 1.0022472
L36: 45474 | M36: 0.49833962
L37: 45505 | M37: 0.62256358
L38: 45536 | M38: -5.8156425
L39: 45566 | M39: -0.57879349
L40: 45597 | M40: -0.31746032
N42: Yearly ROI%
N43: Year
N44: {='ROI%'!$L$76} -> 45292 | O44: 0.12485511
P46: Player - Wins
R47: Outcome | S47: Loss | T47: Pending | U47: Place | V47: Win | W47: Grand Total
P48: Place Terms | Q48: Player | R48: Price | V48: Return (Sum)
R49: 45301 | S49: 0 | W49: 0
Q50: Nick Taylor / Adam Hadwin | S50: 0 | W50: 0
R51: 40-1 | S51: 0 | W51: 0
Q52: Robert MacIntyre | S52: 0 | W52: 0
P53: 1/4 Top 3 | S53: 0 | W53: 0
R54: 30-1 | S54: 0 | W54: 0
Q55: Adam Scott | S55: 0 | W55: 0
R56: 66-1 | S56: 0 | W56: 0
Q57: Adrien Saddier | S57: 0 | W57: 0
R58: 20-1 | U58: 0 | W58: 0
R59: 35-1 | S59: 0 | W59: 0
R60: 40-1 | V60: 0 | W60: 0
Q61: Akshay Bhatia | S61: 0 | U61: 0 | V61: 0 | W61: 0
R62: 389-1 | S62: 0 | W62: 0
Q63: Akshay Bhatia/ Joe Dean | S63: 0 | W63: 0
R64: 50-1 | S64: 0 | W64: 0
R65: 75-1 | S65: 0 | W65: 0
Q66: Alex Fitzpatrick | S66: 0 | W66: 0
R67: 60-1 | S67: 0 | W67: 0
Q68: Alex Smalley | S68: 0 | W68: 0
R69: 70-1 | S69: 0 | W69: 0
Q70: Andrea Pavan | S70: 0 | W70: 0
R71: 70-1 | S71: 0 | W71: 0
Q72: Andy Sullivan | S72: 0 | W72: 0
R73: 45-1 | S73: 0 | W73: 0
Q74: Beau Hossler | S74: 0 | W74: 0
R75: 18-1 | S75: 0 | W75: 0
Q76: Bernd Wiesberger | S76: 0 | W76: 0
R77: 25-1 | S77: 0 | W77: 0
Q78: Billy Horshel | S78: 0 | W78: 0
